{
  "history": [
    {
      "time": "2026-04-30T11:08:30.591004+00:00",
      "balance": 9554.94,
      "equity": 9795.97
    },
    {
      "time": "2026-04-30T11:08:31.610297+00:00",
      "balance": 9554.94,
      "equity": 9795.7
    },
    {
      "time": "2026-04-30T15:50:36.290302+00:00",
      "balance": 6235.07,
      "equity": 6019.43
    },
    {
      "time": "2026-04-30T15:52:21.031239+00:00",
      "balance": 6235.07,
      "equity": 6120.9
    },
    {
      "time": "2026-04-30T15:54:06.028988+00:00",
      "balance": 6235.07,
      "equity": 6214.28
    },
    {
      "time": "2026-04-30T15:55:48.762189+00:00",
      "balance": 6235.07,
      "equity": 6334.27
    },
    {
      "time": "2026-04-30T15:57:36.599159+00:00",
      "balance": 6235.07,
      "equity": 6346.78
    },
    {
      "time": "2026-04-30T15:57:47.019632+00:00",
      "balance": 6235.07,
      "equity": 6300.64
    },
    {
      "time": "2026-04-30T15:57:57.290548+00:00",
      "balance": 6235.07,
      "equity": 6277.36
    },
    {
      "time": "2026-04-30T15:58:07.787407+00:00",
      "balance": 6235.07,
      "equity": 6286.28
    },
    {
      "time": "2026-04-30T15:58:18.132389+00:00",
      "balance": 6235.07,
      "equity": 6284.3
    },
    {
      "time": "2026-04-30T15:58:28.413626+00:00",
      "balance": 6235.07,
      "equity": 6312.59
    },
    {
      "time": "2026-04-30T15:58:38.677503+00:00",
      "balance": 6235.07,
      "equity": 6296.03
    },
    {
      "time": "2026-04-30T15:58:48.897089+00:00",
      "balance": 6235.07,
      "equity": 6292.72
    },
    {
      "time": "2026-04-30T15:58:59.578255+00:00",
      "balance": 6235.07,
      "equity": 6269.32
    },
    {
      "time": "2026-04-30T15:59:09.799147+00:00",
      "balance": 6235.07,
      "equity": 6297.93
    },
    {
      "time": "2026-04-30T15:59:20.020861+00:00",
      "balance": 6235.07,
      "equity": 6293.1
    },
    {
      "time": "2026-04-30T15:59:30.252345+00:00",
      "balance": 6235.07,
      "equity": 6257.47
    },
    {
      "time": "2026-04-30T15:59:40.490123+00:00",
      "balance": 6235.07,
      "equity": 6252.91
    },
    {
      "time": "2026-04-30T15:59:50.731907+00:00",
      "balance": 6235.07,
      "equity": 6222.47
    },
    {
      "time": "2026-04-30T16:00:01.134089+00:00",
      "balance": 6235.07,
      "equity": 6238.42
    },
    {
      "time": "2026-04-30T16:00:11.414018+00:00",
      "balance": 6235.07,
      "equity": 6155.64
    },
    {
      "time": "2026-04-30T16:00:21.657735+00:00",
      "balance": 6235.07,
      "equity": 6181.0
    },
    {
      "time": "2026-04-30T16:00:31.943383+00:00",
      "balance": 6235.07,
      "equity": 6204.65
    },
    {
      "time": "2026-04-30T16:00:45.962738+00:00",
      "balance": 6235.07,
      "equity": 6186.26
    },
    {
      "time": "2026-04-30T16:00:56.230368+00:00",
      "balance": 6235.07,
      "equity": 6176.86
    },
    {
      "time": "2026-04-30T16:01:07.426050+00:00",
      "balance": 6235.07,
      "equity": 6182.21
    },
    {
      "time": "2026-04-30T16:01:17.678266+00:00",
      "balance": 6235.07,
      "equity": 6133.86
    },
    {
      "time": "2026-04-30T16:01:28.016881+00:00",
      "balance": 6235.07,
      "equity": 6109.67
    },
    {
      "time": "2026-04-30T16:01:38.282106+00:00",
      "balance": 6235.07,
      "equity": 6114.53
    },
    {
      "time": "2026-04-30T16:01:48.540881+00:00",
      "balance": 6235.07,
      "equity": 6014.34
    },
    {
      "time": "2026-04-30T16:01:58.808474+00:00",
      "balance": 6235.07,
      "equity": 6000.57
    },
    {
      "time": "2026-04-30T16:02:09.072809+00:00",
      "balance": 6235.07,
      "equity": 5960.96
    },
    {
      "time": "2026-04-30T16:02:19.344892+00:00",
      "balance": 6235.07,
      "equity": 5954.07
    },
    {
      "time": "2026-04-30T16:02:29.627442+00:00",
      "balance": 6235.07,
      "equity": 5904.94
    },
    {
      "time": "2026-04-30T16:02:39.924151+00:00",
      "balance": 6235.07,
      "equity": 5910.04
    },
    {
      "time": "2026-04-30T16:02:50.237690+00:00",
      "balance": 6235.07,
      "equity": 5922.44
    },
    {
      "time": "2026-04-30T16:03:00.484465+00:00",
      "balance": 6235.07,
      "equity": 5927.66
    },
    {
      "time": "2026-04-30T16:03:10.977283+00:00",
      "balance": 6235.07,
      "equity": 5947.06
    },
    {
      "time": "2026-04-30T16:03:21.235001+00:00",
      "balance": 6235.07,
      "equity": 5957.02
    },
    {
      "time": "2026-04-30T16:03:31.494337+00:00",
      "balance": 6235.07,
      "equity": 5972.44
    },
    {
      "time": "2026-04-30T16:03:41.785738+00:00",
      "balance": 6235.07,
      "equity": 5963.05
    },
    {
      "time": "2026-04-30T16:03:52.076599+00:00",
      "balance": 6235.07,
      "equity": 5987.81
    },
    {
      "time": "2026-04-30T16:04:02.387197+00:00",
      "balance": 6235.07,
      "equity": 6037.05
    },
    {
      "time": "2026-04-30T16:04:12.685362+00:00",
      "balance": 6235.07,
      "equity": 6056.75
    },
    {
      "time": "2026-04-30T16:04:22.967482+00:00",
      "balance": 6235.07,
      "equity": 6093.78
    },
    {
      "time": "2026-04-30T16:04:33.333794+00:00",
      "balance": 6235.07,
      "equity": 6099.73
    },
    {
      "time": "2026-04-30T16:04:43.643946+00:00",
      "balance": 6235.07,
      "equity": 6143.68
    },
    {
      "time": "2026-04-30T16:04:53.945589+00:00",
      "balance": 6235.07,
      "equity": 6141.02
    },
    {
      "time": "2026-04-30T16:05:04.215381+00:00",
      "balance": 6235.07,
      "equity": 6135.48
    },
    {
      "time": "2026-04-30T16:05:14.524136+00:00",
      "balance": 6235.07,
      "equity": 6172.78
    },
    {
      "time": "2026-04-30T16:05:24.784150+00:00",
      "balance": 6235.07,
      "equity": 6190.41
    },
    {
      "time": "2026-04-30T16:05:25.809241+00:00",
      "balance": 6235.07,
      "equity": 6178.17
    },
    {
      "time": "2026-04-30T16:05:26.838861+00:00",
      "balance": 6235.07,
      "equity": 6166.01
    },
    {
      "time": "2026-04-30T16:05:27.863706+00:00",
      "balance": 6235.07,
      "equity": 6149.42
    },
    {
      "time": "2026-04-30T16:05:28.888270+00:00",
      "balance": 6235.07,
      "equity": 6153.81
    },
    {
      "time": "2026-04-30T16:05:29.913542+00:00",
      "balance": 6235.07,
      "equity": 6164.13
    },
    {
      "time": "2026-04-30T16:05:30.939056+00:00",
      "balance": 6235.07,
      "equity": 6172.44
    },
    {
      "time": "2026-04-30T16:05:31.962830+00:00",
      "balance": 6235.07,
      "equity": 6152.88
    },
    {
      "time": "2026-04-30T16:05:32.988634+00:00",
      "balance": 6235.07,
      "equity": 6150.1
    },
    {
      "time": "2026-04-30T16:05:34.012620+00:00",
      "balance": 6235.07,
      "equity": 6148.88
    },
    {
      "time": "2026-04-30T16:05:35.067222+00:00",
      "balance": 6235.07,
      "equity": 6160.4
    },
    {
      "time": "2026-04-30T16:05:36.096050+00:00",
      "balance": 6235.07,
      "equity": 6148.36
    },
    {
      "time": "2026-04-30T16:05:37.121717+00:00",
      "balance": 6235.07,
      "equity": 6151.04
    },
    {
      "time": "2026-04-30T16:05:38.146193+00:00",
      "balance": 6235.07,
      "equity": 6139.02
    },
    {
      "time": "2026-04-30T16:05:39.171490+00:00",
      "balance": 6235.07,
      "equity": 6145.32
    },
    {
      "time": "2026-04-30T16:05:40.196870+00:00",
      "balance": 6235.07,
      "equity": 6162.03
    },
    {
      "time": "2026-04-30T16:05:41.222555+00:00",
      "balance": 6235.07,
      "equity": 6160.1
    },
    {
      "time": "2026-04-30T16:05:42.247117+00:00",
      "balance": 6235.07,
      "equity": 6157.52
    },
    {
      "time": "2026-04-30T16:05:43.273551+00:00",
      "balance": 6235.07,
      "equity": 6151.24
    },
    {
      "time": "2026-04-30T16:05:44.299518+00:00",
      "balance": 6235.07,
      "equity": 6161.89
    },
    {
      "time": "2026-04-30T16:05:45.357126+00:00",
      "balance": 6235.07,
      "equity": 6155.31
    },
    {
      "time": "2026-04-30T16:05:46.382676+00:00",
      "balance": 6235.07,
      "equity": 6148.79
    },
    {
      "time": "2026-04-30T16:05:47.406836+00:00",
      "balance": 6235.07,
      "equity": 6150.07
    },
    {
      "time": "2026-04-30T16:05:48.431952+00:00",
      "balance": 6235.07,
      "equity": 6147.7
    },
    {
      "time": "2026-04-30T16:05:49.459331+00:00",
      "balance": 6235.07,
      "equity": 6139.07
    },
    {
      "time": "2026-04-30T16:05:50.486676+00:00",
      "balance": 6235.07,
      "equity": 6162.39
    },
    {
      "time": "2026-04-30T16:05:51.511555+00:00",
      "balance": 6235.07,
      "equity": 6144.57
    },
    {
      "time": "2026-04-30T16:05:52.538764+00:00",
      "balance": 6235.07,
      "equity": 6135.49
    },
    {
      "time": "2026-04-30T16:05:53.566548+00:00",
      "balance": 6235.07,
      "equity": 6131.43
    },
    {
      "time": "2026-04-30T16:05:54.592448+00:00",
      "balance": 6235.07,
      "equity": 6143.33
    },
    {
      "time": "2026-04-30T16:05:55.619519+00:00",
      "balance": 6235.07,
      "equity": 6145.31
    },
    {
      "time": "2026-04-30T16:05:56.647444+00:00",
      "balance": 6235.07,
      "equity": 6160.31
    },
    {
      "time": "2026-04-30T16:05:57.675926+00:00",
      "balance": 6235.07,
      "equity": 6166.5
    },
    {
      "time": "2026-04-30T16:05:58.744016+00:00",
      "balance": 6235.07,
      "equity": 6160.62
    },
    {
      "time": "2026-04-30T16:05:59.771789+00:00",
      "balance": 6235.07,
      "equity": 6133.87
    },
    {
      "time": "2026-04-30T16:06:00.798399+00:00",
      "balance": 6235.07,
      "equity": 6131.12
    },
    {
      "time": "2026-04-30T16:06:01.824403+00:00",
      "balance": 6235.07,
      "equity": 6136.86
    },
    {
      "time": "2026-04-30T16:06:02.850434+00:00",
      "balance": 6235.07,
      "equity": 6130.14
    },
    {
      "time": "2026-04-30T16:06:03.876734+00:00",
      "balance": 6235.07,
      "equity": 6134.68
    },
    {
      "time": "2026-04-30T16:06:04.969023+00:00",
      "balance": 6235.07,
      "equity": 6132.84
    },
    {
      "time": "2026-04-30T16:06:05.995348+00:00",
      "balance": 6235.07,
      "equity": 6132.18
    },
    {
      "time": "2026-04-30T16:06:07.022008+00:00",
      "balance": 6235.07,
      "equity": 6116.82
    },
    {
      "time": "2026-04-30T16:06:08.048338+00:00",
      "balance": 6235.07,
      "equity": 6119.24
    },
    {
      "time": "2026-04-30T16:06:09.073949+00:00",
      "balance": 6235.07,
      "equity": 6124.6
    },
    {
      "time": "2026-04-30T16:06:10.099772+00:00",
      "balance": 6235.07,
      "equity": 6122.11
    },
    {
      "time": "2026-04-30T16:06:11.125994+00:00",
      "balance": 6235.07,
      "equity": 6112.49
    },
    {
      "time": "2026-04-30T16:06:12.150968+00:00",
      "balance": 6235.07,
      "equity": 6099.63
    },
    {
      "time": "2026-04-30T16:06:13.177243+00:00",
      "balance": 6235.07,
      "equity": 6101.68
    },
    {
      "time": "2026-04-30T16:06:14.202169+00:00",
      "balance": 6235.07,
      "equity": 6094.01
    },
    {
      "time": "2026-04-30T16:06:15.292404+00:00",
      "balance": 6235.07,
      "equity": 6096.41
    },
    {
      "time": "2026-04-30T16:06:16.314765+00:00",
      "balance": 6235.07,
      "equity": 6092.61
    },
    {
      "time": "2026-04-30T16:06:17.337784+00:00",
      "balance": 6235.07,
      "equity": 6089.05
    },
    {
      "time": "2026-04-30T16:06:18.363369+00:00",
      "balance": 6235.07,
      "equity": 6084.84
    },
    {
      "time": "2026-04-30T16:06:19.384807+00:00",
      "balance": 6235.07,
      "equity": 6084.43
    },
    {
      "time": "2026-04-30T16:06:20.407697+00:00",
      "balance": 6235.07,
      "equity": 6086.55
    },
    {
      "time": "2026-04-30T16:06:21.429934+00:00",
      "balance": 6235.07,
      "equity": 6092.72
    },
    {
      "time": "2026-04-30T16:06:22.452211+00:00",
      "balance": 6235.07,
      "equity": 6092.0
    },
    {
      "time": "2026-04-30T16:06:23.477305+00:00",
      "balance": 6235.07,
      "equity": 6108.94
    },
    {
      "time": "2026-04-30T16:06:24.497178+00:00",
      "balance": 6235.07,
      "equity": 6106.51
    },
    {
      "time": "2026-04-30T16:06:25.523452+00:00",
      "balance": 6235.07,
      "equity": 6112.24
    },
    {
      "time": "2026-04-30T16:06:26.544039+00:00",
      "balance": 6235.07,
      "equity": 6112.62
    },
    {
      "time": "2026-04-30T16:06:27.567861+00:00",
      "balance": 6235.07,
      "equity": 6146.21
    },
    {
      "time": "2026-04-30T16:06:28.597790+00:00",
      "balance": 6235.07,
      "equity": 6160.5
    },
    {
      "time": "2026-04-30T16:06:29.622710+00:00",
      "balance": 6235.07,
      "equity": 6170.64
    },
    {
      "time": "2026-04-30T16:06:30.649145+00:00",
      "balance": 6235.07,
      "equity": 6171.48
    },
    {
      "time": "2026-04-30T16:06:31.674350+00:00",
      "balance": 6235.07,
      "equity": 6172.87
    },
    {
      "time": "2026-04-30T16:06:32.699891+00:00",
      "balance": 6235.07,
      "equity": 6181.99
    },
    {
      "time": "2026-04-30T16:06:33.734433+00:00",
      "balance": 6235.07,
      "equity": 6187.29
    },
    {
      "time": "2026-04-30T16:06:34.769864+00:00",
      "balance": 6235.07,
      "equity": 6192.02
    },
    {
      "time": "2026-04-30T16:06:35.821417+00:00",
      "balance": 6235.07,
      "equity": 6184.83
    },
    {
      "time": "2026-04-30T16:06:36.925012+00:00",
      "balance": 6235.07,
      "equity": 6187.47
    },
    {
      "time": "2026-04-30T16:06:37.966514+00:00",
      "balance": 6235.07,
      "equity": 6185.56
    },
    {
      "time": "2026-04-30T16:06:38.990957+00:00",
      "balance": 6235.07,
      "equity": 6192.63
    },
    {
      "time": "2026-04-30T16:06:40.013757+00:00",
      "balance": 6235.07,
      "equity": 6200.34
    },
    {
      "time": "2026-04-30T16:06:41.037151+00:00",
      "balance": 6235.07,
      "equity": 6198.7
    },
    {
      "time": "2026-04-30T16:06:42.138199+00:00",
      "balance": 6235.07,
      "equity": 6243.56
    },
    {
      "time": "2026-04-30T16:06:43.160868+00:00",
      "balance": 6235.07,
      "equity": 6254.98
    },
    {
      "time": "2026-04-30T16:06:44.183050+00:00",
      "balance": 6235.07,
      "equity": 6246.23
    },
    {
      "time": "2026-04-30T16:06:45.206530+00:00",
      "balance": 6235.07,
      "equity": 6224.93
    },
    {
      "time": "2026-04-30T16:06:46.238436+00:00",
      "balance": 6235.07,
      "equity": 6206.29
    },
    {
      "time": "2026-04-30T16:06:47.262068+00:00",
      "balance": 6235.07,
      "equity": 6196.1
    },
    {
      "time": "2026-04-30T16:06:48.283147+00:00",
      "balance": 6235.07,
      "equity": 6209.76
    },
    {
      "time": "2026-04-30T16:06:49.305705+00:00",
      "balance": 6235.07,
      "equity": 6215.82
    },
    {
      "time": "2026-04-30T16:06:50.327744+00:00",
      "balance": 6235.07,
      "equity": 6209.09
    },
    {
      "time": "2026-04-30T16:06:51.348706+00:00",
      "balance": 6235.07,
      "equity": 6190.51
    },
    {
      "time": "2026-04-30T16:06:52.374102+00:00",
      "balance": 6235.07,
      "equity": 6194.59
    },
    {
      "time": "2026-04-30T16:06:53.396519+00:00",
      "balance": 6235.07,
      "equity": 6190.19
    },
    {
      "time": "2026-04-30T16:06:54.417984+00:00",
      "balance": 6235.07,
      "equity": 6197.25
    },
    {
      "time": "2026-04-30T16:06:55.440997+00:00",
      "balance": 6235.07,
      "equity": 6201.12
    },
    {
      "time": "2026-04-30T16:06:56.464609+00:00",
      "balance": 6235.07,
      "equity": 6185.79
    },
    {
      "time": "2026-04-30T16:06:57.486948+00:00",
      "balance": 6235.07,
      "equity": 6188.04
    },
    {
      "time": "2026-04-30T16:06:58.509410+00:00",
      "balance": 6235.07,
      "equity": 6190.5
    },
    {
      "time": "2026-04-30T16:06:59.533054+00:00",
      "balance": 6235.07,
      "equity": 6176.75
    },
    {
      "time": "2026-04-30T16:07:00.554877+00:00",
      "balance": 6235.07,
      "equity": 6162.86
    },
    {
      "time": "2026-04-30T16:07:01.577948+00:00",
      "balance": 6235.07,
      "equity": 6158.27
    },
    {
      "time": "2026-04-30T16:07:02.600316+00:00",
      "balance": 6235.07,
      "equity": 6156.21
    },
    {
      "time": "2026-04-30T16:07:03.623021+00:00",
      "balance": 6235.07,
      "equity": 6165.09
    },
    {
      "time": "2026-04-30T16:07:04.644661+00:00",
      "balance": 6235.07,
      "equity": 6146.14
    },
    {
      "time": "2026-04-30T16:07:05.668394+00:00",
      "balance": 6235.07,
      "equity": 6117.04
    },
    {
      "time": "2026-04-30T16:07:06.692166+00:00",
      "balance": 6235.07,
      "equity": 6122.72
    },
    {
      "time": "2026-04-30T16:07:07.716314+00:00",
      "balance": 6235.07,
      "equity": 6117.72
    },
    {
      "time": "2026-04-30T16:07:08.740977+00:00",
      "balance": 6235.07,
      "equity": 6105.68
    },
    {
      "time": "2026-04-30T16:07:09.765774+00:00",
      "balance": 6235.07,
      "equity": 6101.8
    },
    {
      "time": "2026-04-30T16:07:10.787317+00:00",
      "balance": 6235.07,
      "equity": 6109.19
    },
    {
      "time": "2026-04-30T16:07:11.811685+00:00",
      "balance": 6235.07,
      "equity": 6108.66
    },
    {
      "time": "2026-04-30T16:07:12.837600+00:00",
      "balance": 6235.07,
      "equity": 6100.31
    },
    {
      "time": "2026-04-30T16:07:13.864136+00:00",
      "balance": 6235.07,
      "equity": 6091.48
    },
    {
      "time": "2026-04-30T16:07:14.888137+00:00",
      "balance": 6235.07,
      "equity": 6099.1
    },
    {
      "time": "2026-04-30T16:07:15.915689+00:00",
      "balance": 6235.07,
      "equity": 6102.18
    },
    {
      "time": "2026-04-30T16:07:16.948549+00:00",
      "balance": 6235.07,
      "equity": 6179.4
    },
    {
      "time": "2026-04-30T16:07:17.971169+00:00",
      "balance": 6235.07,
      "equity": 6159.79
    },
    {
      "time": "2026-04-30T16:07:18.994351+00:00",
      "balance": 6235.07,
      "equity": 6163.19
    },
    {
      "time": "2026-04-30T16:07:20.017631+00:00",
      "balance": 6235.07,
      "equity": 6171.22
    },
    {
      "time": "2026-04-30T16:07:21.039017+00:00",
      "balance": 6235.07,
      "equity": 6161.64
    },
    {
      "time": "2026-04-30T16:07:22.061592+00:00",
      "balance": 6235.07,
      "equity": 6167.06
    },
    {
      "time": "2026-04-30T16:07:23.083921+00:00",
      "balance": 6235.07,
      "equity": 6162.27
    },
    {
      "time": "2026-04-30T16:07:24.105051+00:00",
      "balance": 6235.07,
      "equity": 6156.69
    },
    {
      "time": "2026-04-30T16:07:25.136833+00:00",
      "balance": 6235.07,
      "equity": 6164.28
    },
    {
      "time": "2026-04-30T16:07:26.159654+00:00",
      "balance": 6235.07,
      "equity": 6162.7
    },
    {
      "time": "2026-04-30T16:07:27.182600+00:00",
      "balance": 6235.07,
      "equity": 6153.96
    },
    {
      "time": "2026-04-30T16:07:28.214765+00:00",
      "balance": 6235.07,
      "equity": 6155.06
    },
    {
      "time": "2026-04-30T16:07:29.236161+00:00",
      "balance": 6235.07,
      "equity": 6165.33
    },
    {
      "time": "2026-04-30T16:07:30.260899+00:00",
      "balance": 6235.07,
      "equity": 6175.89
    },
    {
      "time": "2026-04-30T16:07:31.285024+00:00",
      "balance": 6235.07,
      "equity": 6163.86
    },
    {
      "time": "2026-04-30T16:07:32.307813+00:00",
      "balance": 6235.07,
      "equity": 6164.57
    },
    {
      "time": "2026-04-30T16:07:33.331789+00:00",
      "balance": 6235.07,
      "equity": 6164.51
    },
    {
      "time": "2026-04-30T16:07:34.355331+00:00",
      "balance": 6235.07,
      "equity": 6161.43
    },
    {
      "time": "2026-04-30T16:07:35.379581+00:00",
      "balance": 6235.07,
      "equity": 6155.99
    },
    {
      "time": "2026-04-30T16:07:36.402417+00:00",
      "balance": 6235.07,
      "equity": 6155.99
    },
    {
      "time": "2026-04-30T16:07:37.428710+00:00",
      "balance": 6235.07,
      "equity": 6142.28
    },
    {
      "time": "2026-04-30T16:07:38.457902+00:00",
      "balance": 6235.07,
      "equity": 6126.82
    },
    {
      "time": "2026-04-30T16:07:39.481068+00:00",
      "balance": 6235.07,
      "equity": 6137.8
    },
    {
      "time": "2026-04-30T16:07:40.528270+00:00",
      "balance": 6235.07,
      "equity": 6128.04
    },
    {
      "time": "2026-04-30T16:07:41.553592+00:00",
      "balance": 6235.07,
      "equity": 6134.3
    },
    {
      "time": "2026-04-30T16:07:42.576934+00:00",
      "balance": 6235.07,
      "equity": 6123.47
    },
    {
      "time": "2026-04-30T16:07:43.598864+00:00",
      "balance": 6235.07,
      "equity": 6116.56
    },
    {
      "time": "2026-04-30T16:07:44.622907+00:00",
      "balance": 6235.07,
      "equity": 6117.27
    },
    {
      "time": "2026-04-30T16:07:45.644665+00:00",
      "balance": 6235.07,
      "equity": 6120.33
    },
    {
      "time": "2026-04-30T16:07:46.668920+00:00",
      "balance": 6235.07,
      "equity": 6126.23
    },
    {
      "time": "2026-04-30T16:07:47.690534+00:00",
      "balance": 6235.07,
      "equity": 6111.4
    },
    {
      "time": "2026-04-30T16:07:48.714857+00:00",
      "balance": 6235.07,
      "equity": 6108.08
    },
    {
      "time": "2026-04-30T16:07:49.737743+00:00",
      "balance": 6235.07,
      "equity": 6100.85
    },
    {
      "time": "2026-04-30T16:07:50.760928+00:00",
      "balance": 6235.07,
      "equity": 6100.97
    },
    {
      "time": "2026-04-30T16:07:51.785328+00:00",
      "balance": 6235.07,
      "equity": 6115.51
    },
    {
      "time": "2026-04-30T16:07:52.809579+00:00",
      "balance": 6235.07,
      "equity": 6111.93
    },
    {
      "time": "2026-04-30T16:07:53.834298+00:00",
      "balance": 6235.07,
      "equity": 6103.73
    },
    {
      "time": "2026-04-30T16:07:54.857468+00:00",
      "balance": 6235.07,
      "equity": 6121.88
    },
    {
      "time": "2026-04-30T16:07:55.879293+00:00",
      "balance": 6235.07,
      "equity": 6130.41
    },
    {
      "time": "2026-04-30T16:07:56.903430+00:00",
      "balance": 6235.07,
      "equity": 6124.64
    },
    {
      "time": "2026-04-30T16:07:57.925110+00:00",
      "balance": 6235.07,
      "equity": 6129.81
    },
    {
      "time": "2026-04-30T16:07:58.948616+00:00",
      "balance": 6235.07,
      "equity": 6138.14
    },
    {
      "time": "2026-04-30T16:07:59.970722+00:00",
      "balance": 6235.07,
      "equity": 6155.74
    },
    {
      "time": "2026-04-30T16:08:00.994200+00:00",
      "balance": 6235.07,
      "equity": 6150.64
    },
    {
      "time": "2026-04-30T16:08:02.018106+00:00",
      "balance": 6235.07,
      "equity": 6151.62
    },
    {
      "time": "2026-04-30T16:08:03.040729+00:00",
      "balance": 6235.07,
      "equity": 6137.08
    },
    {
      "time": "2026-04-30T16:08:04.063752+00:00",
      "balance": 6235.07,
      "equity": 6141.36
    },
    {
      "time": "2026-04-30T16:08:05.091668+00:00",
      "balance": 6235.07,
      "equity": 6136.27
    },
    {
      "time": "2026-04-30T16:08:06.116696+00:00",
      "balance": 6235.07,
      "equity": 6136.26
    },
    {
      "time": "2026-04-30T16:08:07.142251+00:00",
      "balance": 6235.07,
      "equity": 6140.55
    },
    {
      "time": "2026-04-30T16:08:08.166269+00:00",
      "balance": 6235.07,
      "equity": 6138.05
    },
    {
      "time": "2026-04-30T16:08:09.187693+00:00",
      "balance": 6235.07,
      "equity": 6140.18
    },
    {
      "time": "2026-04-30T16:08:10.208735+00:00",
      "balance": 6235.07,
      "equity": 6138.64
    },
    {
      "time": "2026-04-30T16:08:11.231256+00:00",
      "balance": 6235.07,
      "equity": 6140.25
    },
    {
      "time": "2026-04-30T16:08:12.255689+00:00",
      "balance": 6235.07,
      "equity": 6142.32
    },
    {
      "time": "2026-04-30T16:08:13.279930+00:00",
      "balance": 6235.07,
      "equity": 6133.71
    },
    {
      "time": "2026-04-30T16:08:14.302780+00:00",
      "balance": 6235.07,
      "equity": 6134.59
    },
    {
      "time": "2026-04-30T16:08:15.330564+00:00",
      "balance": 6235.07,
      "equity": 6137.05
    },
    {
      "time": "2026-04-30T16:08:16.353062+00:00",
      "balance": 6235.07,
      "equity": 6142.53
    },
    {
      "time": "2026-04-30T16:08:17.375037+00:00",
      "balance": 6235.07,
      "equity": 6146.04
    },
    {
      "time": "2026-04-30T16:08:18.399231+00:00",
      "balance": 6235.07,
      "equity": 6153.56
    },
    {
      "time": "2026-04-30T16:08:19.421306+00:00",
      "balance": 6235.07,
      "equity": 6153.65
    },
    {
      "time": "2026-04-30T16:08:20.447256+00:00",
      "balance": 6235.07,
      "equity": 6151.88
    },
    {
      "time": "2026-04-30T16:08:21.470784+00:00",
      "balance": 6235.07,
      "equity": 6153.25
    },
    {
      "time": "2026-04-30T16:08:22.495332+00:00",
      "balance": 6235.07,
      "equity": 6155.04
    },
    {
      "time": "2026-04-30T16:08:23.517319+00:00",
      "balance": 6235.07,
      "equity": 6148.64
    },
    {
      "time": "2026-04-30T16:08:24.538444+00:00",
      "balance": 6235.07,
      "equity": 6146.09
    },
    {
      "time": "2026-04-30T16:08:25.564980+00:00",
      "balance": 6235.07,
      "equity": 6140.76
    },
    {
      "time": "2026-04-30T16:08:26.587225+00:00",
      "balance": 6235.07,
      "equity": 6149.52
    },
    {
      "time": "2026-04-30T16:08:27.678431+00:00",
      "balance": 6235.07,
      "equity": 6160.31
    },
    {
      "time": "2026-04-30T16:08:28.700158+00:00",
      "balance": 6235.07,
      "equity": 6158.85
    },
    {
      "time": "2026-04-30T16:08:29.721661+00:00",
      "balance": 6235.07,
      "equity": 6159.44
    },
    {
      "time": "2026-04-30T16:08:30.744909+00:00",
      "balance": 6235.07,
      "equity": 6161.15
    },
    {
      "time": "2026-04-30T16:08:31.766980+00:00",
      "balance": 6235.07,
      "equity": 6173.94
    },
    {
      "time": "2026-04-30T16:08:32.791805+00:00",
      "balance": 6235.07,
      "equity": 6154.41
    },
    {
      "time": "2026-04-30T16:08:33.815319+00:00",
      "balance": 6235.07,
      "equity": 6147.7
    },
    {
      "time": "2026-04-30T16:08:34.839619+00:00",
      "balance": 6235.07,
      "equity": 6147.25
    },
    {
      "time": "2026-04-30T16:08:35.861642+00:00",
      "balance": 6235.07,
      "equity": 6136.12
    },
    {
      "time": "2026-04-30T16:08:36.884514+00:00",
      "balance": 6235.07,
      "equity": 6135.73
    },
    {
      "time": "2026-04-30T16:08:37.907009+00:00",
      "balance": 6235.07,
      "equity": 6137.11
    },
    {
      "time": "2026-04-30T16:08:38.930101+00:00",
      "balance": 6235.07,
      "equity": 6134.89
    },
    {
      "time": "2026-04-30T16:08:39.952707+00:00",
      "balance": 6235.07,
      "equity": 6133.51
    },
    {
      "time": "2026-04-30T16:08:40.980927+00:00",
      "balance": 6235.07,
      "equity": 6136.61
    },
    {
      "time": "2026-04-30T16:08:42.004063+00:00",
      "balance": 6235.07,
      "equity": 6130.51
    },
    {
      "time": "2026-04-30T16:08:43.027443+00:00",
      "balance": 6235.07,
      "equity": 6137.88
    },
    {
      "time": "2026-04-30T16:08:44.050439+00:00",
      "balance": 6235.07,
      "equity": 6131.04
    },
    {
      "time": "2026-04-30T16:08:45.075388+00:00",
      "balance": 6235.07,
      "equity": 6132.49
    },
    {
      "time": "2026-04-30T16:08:46.099907+00:00",
      "balance": 6235.07,
      "equity": 6118.27
    },
    {
      "time": "2026-04-30T16:08:47.126472+00:00",
      "balance": 6235.07,
      "equity": 6125.27
    },
    {
      "time": "2026-04-30T16:08:48.149136+00:00",
      "balance": 6235.07,
      "equity": 6124.95
    },
    {
      "time": "2026-04-30T16:08:49.178660+00:00",
      "balance": 6235.07,
      "equity": 6132.21
    },
    {
      "time": "2026-04-30T16:08:50.206380+00:00",
      "balance": 6235.07,
      "equity": 6137.06
    },
    {
      "time": "2026-04-30T16:08:51.230682+00:00",
      "balance": 6235.07,
      "equity": 6128.57
    },
    {
      "time": "2026-04-30T16:08:52.254132+00:00",
      "balance": 6235.07,
      "equity": 6129.01
    },
    {
      "time": "2026-04-30T16:08:53.278653+00:00",
      "balance": 6235.07,
      "equity": 6126.56
    },
    {
      "time": "2026-04-30T16:08:54.303687+00:00",
      "balance": 6235.07,
      "equity": 6114.71
    },
    {
      "time": "2026-04-30T16:08:55.328324+00:00",
      "balance": 6235.07,
      "equity": 6118.94
    },
    {
      "time": "2026-04-30T16:08:56.351619+00:00",
      "balance": 6235.07,
      "equity": 6114.31
    },
    {
      "time": "2026-04-30T16:08:57.377980+00:00",
      "balance": 6235.07,
      "equity": 6114.31
    },
    {
      "time": "2026-04-30T16:08:58.403684+00:00",
      "balance": 6235.07,
      "equity": 6116.86
    },
    {
      "time": "2026-04-30T16:08:59.426685+00:00",
      "balance": 6235.07,
      "equity": 6111.06
    },
    {
      "time": "2026-04-30T16:09:00.450453+00:00",
      "balance": 6235.07,
      "equity": 6106.16
    },
    {
      "time": "2026-04-30T16:09:01.475394+00:00",
      "balance": 6235.07,
      "equity": 6108.53
    },
    {
      "time": "2026-04-30T16:09:02.499401+00:00",
      "balance": 6235.07,
      "equity": 6108.06
    },
    {
      "time": "2026-04-30T16:09:03.523979+00:00",
      "balance": 6235.07,
      "equity": 6097.43
    },
    {
      "time": "2026-04-30T16:09:04.546377+00:00",
      "balance": 6235.07,
      "equity": 6097.32
    },
    {
      "time": "2026-04-30T16:09:05.569604+00:00",
      "balance": 6235.07,
      "equity": 6087.47
    },
    {
      "time": "2026-04-30T16:09:06.592340+00:00",
      "balance": 6235.07,
      "equity": 6088.47
    },
    {
      "time": "2026-04-30T16:09:07.615786+00:00",
      "balance": 6235.07,
      "equity": 6084.05
    },
    {
      "time": "2026-04-30T16:09:08.639227+00:00",
      "balance": 6235.07,
      "equity": 6061.28
    },
    {
      "time": "2026-04-30T16:09:09.661974+00:00",
      "balance": 6235.07,
      "equity": 6064.22
    },
    {
      "time": "2026-04-30T16:09:10.685978+00:00",
      "balance": 6235.07,
      "equity": 6058.34
    },
    {
      "time": "2026-04-30T16:09:11.708666+00:00",
      "balance": 6235.07,
      "equity": 6057.21
    },
    {
      "time": "2026-04-30T16:09:12.733571+00:00",
      "balance": 6235.07,
      "equity": 6054.21
    },
    {
      "time": "2026-04-30T16:09:13.759016+00:00",
      "balance": 6235.07,
      "equity": 6056.18
    },
    {
      "time": "2026-04-30T16:09:14.794315+00:00",
      "balance": 6235.07,
      "equity": 6061.87
    },
    {
      "time": "2026-04-30T16:09:15.830325+00:00",
      "balance": 6235.07,
      "equity": 6072.19
    },
    {
      "time": "2026-04-30T16:09:16.857003+00:00",
      "balance": 6235.07,
      "equity": 6072.1
    },
    {
      "time": "2026-04-30T16:09:17.882853+00:00",
      "balance": 6235.07,
      "equity": 6074.31
    },
    {
      "time": "2026-04-30T16:09:18.959167+00:00",
      "balance": 6235.07,
      "equity": 6079.44
    },
    {
      "time": "2026-04-30T16:09:20.025226+00:00",
      "balance": 6235.07,
      "equity": 6084.18
    },
    {
      "time": "2026-04-30T16:09:21.236916+00:00",
      "balance": 6235.07,
      "equity": 6092.37
    },
    {
      "time": "2026-04-30T16:09:22.263175+00:00",
      "balance": 6235.07,
      "equity": 6090.37
    },
    {
      "time": "2026-04-30T16:09:23.300142+00:00",
      "balance": 6235.07,
      "equity": 6113.34
    },
    {
      "time": "2026-04-30T16:09:24.337327+00:00",
      "balance": 6235.07,
      "equity": 6108.38
    },
    {
      "time": "2026-04-30T16:09:25.379983+00:00",
      "balance": 6235.07,
      "equity": 6109.89
    },
    {
      "time": "2026-04-30T16:09:26.423073+00:00",
      "balance": 6235.07,
      "equity": 6102.22
    },
    {
      "time": "2026-04-30T16:09:27.455939+00:00",
      "balance": 6235.07,
      "equity": 6092.98
    },
    {
      "time": "2026-04-30T16:09:28.491568+00:00",
      "balance": 6235.07,
      "equity": 6097.77
    },
    {
      "time": "2026-04-30T16:09:29.521679+00:00",
      "balance": 6235.07,
      "equity": 6096.9
    },
    {
      "time": "2026-04-30T16:09:30.549151+00:00",
      "balance": 6235.07,
      "equity": 6075.64
    },
    {
      "time": "2026-04-30T16:09:31.575958+00:00",
      "balance": 6235.07,
      "equity": 6085.78
    },
    {
      "time": "2026-04-30T16:09:32.603443+00:00",
      "balance": 6235.07,
      "equity": 6083.55
    },
    {
      "time": "2026-04-30T16:09:33.633318+00:00",
      "balance": 6235.07,
      "equity": 6082.48
    },
    {
      "time": "2026-04-30T16:09:34.667854+00:00",
      "balance": 6235.07,
      "equity": 6073.94
    },
    {
      "time": "2026-04-30T16:09:35.711109+00:00",
      "balance": 6235.07,
      "equity": 6077.5
    },
    {
      "time": "2026-04-30T16:09:36.738017+00:00",
      "balance": 6235.07,
      "equity": 6078.02
    },
    {
      "time": "2026-04-30T16:09:37.768833+00:00",
      "balance": 6235.07,
      "equity": 6079.54
    },
    {
      "time": "2026-04-30T16:09:38.799932+00:00",
      "balance": 6235.07,
      "equity": 6080.07
    },
    {
      "time": "2026-04-30T16:09:39.832916+00:00",
      "balance": 6235.07,
      "equity": 6080.36
    },
    {
      "time": "2026-04-30T16:09:40.863171+00:00",
      "balance": 6235.07,
      "equity": 6079.89
    },
    {
      "time": "2026-04-30T16:09:41.894797+00:00",
      "balance": 6235.07,
      "equity": 6107.32
    },
    {
      "time": "2026-04-30T16:09:42.922156+00:00",
      "balance": 6235.07,
      "equity": 6105.86
    },
    {
      "time": "2026-04-30T16:09:43.951636+00:00",
      "balance": 6235.07,
      "equity": 6103.36
    },
    {
      "time": "2026-04-30T16:09:44.985173+00:00",
      "balance": 6235.07,
      "equity": 6111.24
    },
    {
      "time": "2026-04-30T16:09:46.015367+00:00",
      "balance": 6235.07,
      "equity": 6097.08
    },
    {
      "time": "2026-04-30T16:09:47.046115+00:00",
      "balance": 6235.07,
      "equity": 6097.21
    },
    {
      "time": "2026-04-30T16:09:48.074596+00:00",
      "balance": 6235.07,
      "equity": 6093.38
    },
    {
      "time": "2026-04-30T16:09:49.098772+00:00",
      "balance": 6235.07,
      "equity": 6092.25
    },
    {
      "time": "2026-04-30T16:09:50.127640+00:00",
      "balance": 6235.07,
      "equity": 6093.67
    },
    {
      "time": "2026-04-30T16:09:51.154176+00:00",
      "balance": 6235.07,
      "equity": 6089.42
    },
    {
      "time": "2026-04-30T16:09:52.180552+00:00",
      "balance": 6235.07,
      "equity": 6091.39
    },
    {
      "time": "2026-04-30T16:09:53.214474+00:00",
      "balance": 6235.07,
      "equity": 6096.9
    },
    {
      "time": "2026-04-30T16:09:54.244150+00:00",
      "balance": 6235.07,
      "equity": 6099.84
    },
    {
      "time": "2026-04-30T16:09:55.275920+00:00",
      "balance": 6235.07,
      "equity": 6097.02
    },
    {
      "time": "2026-04-30T16:09:56.305351+00:00",
      "balance": 6235.07,
      "equity": 6096.34
    },
    {
      "time": "2026-04-30T16:09:57.330363+00:00",
      "balance": 6235.07,
      "equity": 6097.47
    },
    {
      "time": "2026-04-30T16:09:58.358704+00:00",
      "balance": 6235.07,
      "equity": 6088.64
    },
    {
      "time": "2026-04-30T16:09:59.383011+00:00",
      "balance": 6235.07,
      "equity": 6088.04
    },
    {
      "time": "2026-04-30T16:10:00.410673+00:00",
      "balance": 6235.07,
      "equity": 6074.02
    },
    {
      "time": "2026-04-30T16:10:01.440877+00:00",
      "balance": 6235.07,
      "equity": 6054.26
    },
    {
      "time": "2026-04-30T16:10:02.469479+00:00",
      "balance": 6235.07,
      "equity": 6045.62
    },
    {
      "time": "2026-04-30T16:10:03.504597+00:00",
      "balance": 6235.07,
      "equity": 6055.25
    },
    {
      "time": "2026-04-30T16:10:04.531991+00:00",
      "balance": 6235.07,
      "equity": 6062.67
    },
    {
      "time": "2026-04-30T16:10:05.559382+00:00",
      "balance": 6235.07,
      "equity": 6068.75
    },
    {
      "time": "2026-04-30T16:10:06.578415+00:00",
      "balance": 6235.07,
      "equity": 6061.92
    },
    {
      "time": "2026-04-30T16:10:07.596705+00:00",
      "balance": 6235.07,
      "equity": 6065.3
    },
    {
      "time": "2026-04-30T16:10:08.627909+00:00",
      "balance": 6235.07,
      "equity": 6070.62
    },
    {
      "time": "2026-04-30T16:10:09.654299+00:00",
      "balance": 6235.07,
      "equity": 6065.83
    },
    {
      "time": "2026-04-30T16:10:10.670786+00:00",
      "balance": 6235.07,
      "equity": 6090.88
    },
    {
      "time": "2026-04-30T16:10:11.698482+00:00",
      "balance": 6235.07,
      "equity": 6092.84
    },
    {
      "time": "2026-04-30T16:10:12.728433+00:00",
      "balance": 6235.07,
      "equity": 6093.29
    },
    {
      "time": "2026-04-30T16:10:13.747240+00:00",
      "balance": 6235.07,
      "equity": 6102.66
    },
    {
      "time": "2026-04-30T16:10:14.774494+00:00",
      "balance": 6235.07,
      "equity": 6094.75
    },
    {
      "time": "2026-04-30T16:10:16.045528+00:00",
      "balance": 6235.07,
      "equity": 6095.34
    },
    {
      "time": "2026-04-30T16:10:17.073018+00:00",
      "balance": 6235.07,
      "equity": 6088.71
    },
    {
      "time": "2026-04-30T16:10:18.099314+00:00",
      "balance": 6235.07,
      "equity": 6087.21
    },
    {
      "time": "2026-04-30T16:10:19.125657+00:00",
      "balance": 6235.07,
      "equity": 6100.65
    },
    {
      "time": "2026-04-30T16:10:20.153028+00:00",
      "balance": 6235.07,
      "equity": 6125.62
    },
    {
      "time": "2026-04-30T16:10:21.179718+00:00",
      "balance": 6235.07,
      "equity": 6135.01
    },
    {
      "time": "2026-04-30T16:10:22.206278+00:00",
      "balance": 6235.07,
      "equity": 6148.12
    },
    {
      "time": "2026-04-30T16:10:23.234371+00:00",
      "balance": 6235.07,
      "equity": 6143.66
    },
    {
      "time": "2026-04-30T16:10:24.260158+00:00",
      "balance": 6235.07,
      "equity": 6155.86
    },
    {
      "time": "2026-04-30T16:10:25.296319+00:00",
      "balance": 6235.07,
      "equity": 6162.97
    },
    {
      "time": "2026-04-30T16:10:26.327986+00:00",
      "balance": 6235.07,
      "equity": 6154.05
    },
    {
      "time": "2026-04-30T16:10:27.357246+00:00",
      "balance": 6235.07,
      "equity": 6161.47
    },
    {
      "time": "2026-04-30T16:10:28.386818+00:00",
      "balance": 6235.07,
      "equity": 6166.91
    },
    {
      "time": "2026-04-30T16:10:29.414839+00:00",
      "balance": 6235.07,
      "equity": 6161.54
    },
    {
      "time": "2026-04-30T16:10:30.439615+00:00",
      "balance": 6235.07,
      "equity": 6157.47
    },
    {
      "time": "2026-04-30T16:10:31.469243+00:00",
      "balance": 6235.07,
      "equity": 6159.57
    },
    {
      "time": "2026-04-30T16:10:32.497722+00:00",
      "balance": 6235.07,
      "equity": 6165.27
    },
    {
      "time": "2026-04-30T16:10:33.524500+00:00",
      "balance": 6235.07,
      "equity": 6165.27
    },
    {
      "time": "2026-04-30T16:10:34.554387+00:00",
      "balance": 6235.07,
      "equity": 6164.21
    },
    {
      "time": "2026-04-30T16:10:35.582584+00:00",
      "balance": 6235.07,
      "equity": 6127.05
    },
    {
      "time": "2026-04-30T16:10:36.614229+00:00",
      "balance": 6235.07,
      "equity": 6127.38
    },
    {
      "time": "2026-04-30T16:10:37.647302+00:00",
      "balance": 6235.07,
      "equity": 6132.25
    },
    {
      "time": "2026-04-30T16:10:38.674362+00:00",
      "balance": 6235.07,
      "equity": 6122.6
    },
    {
      "time": "2026-04-30T16:10:39.702161+00:00",
      "balance": 6235.07,
      "equity": 6096.91
    },
    {
      "time": "2026-04-30T16:10:40.729604+00:00",
      "balance": 6235.07,
      "equity": 6131.44
    },
    {
      "time": "2026-04-30T16:10:41.756107+00:00",
      "balance": 6235.07,
      "equity": 6130.67
    },
    {
      "time": "2026-04-30T16:10:42.782915+00:00",
      "balance": 6235.07,
      "equity": 6128.5
    },
    {
      "time": "2026-04-30T16:10:43.811890+00:00",
      "balance": 6235.07,
      "equity": 6129.24
    },
    {
      "time": "2026-04-30T16:10:44.838910+00:00",
      "balance": 6235.07,
      "equity": 6128.59
    },
    {
      "time": "2026-04-30T16:10:45.868086+00:00",
      "balance": 6235.07,
      "equity": 6116.79
    },
    {
      "time": "2026-04-30T16:10:46.896620+00:00",
      "balance": 6235.07,
      "equity": 6113.89
    },
    {
      "time": "2026-04-30T16:10:47.927320+00:00",
      "balance": 6235.07,
      "equity": 6110.88
    },
    {
      "time": "2026-04-30T16:10:48.954017+00:00",
      "balance": 6235.07,
      "equity": 6111.24
    },
    {
      "time": "2026-04-30T16:10:49.981730+00:00",
      "balance": 6235.07,
      "equity": 6104.88
    },
    {
      "time": "2026-04-30T16:10:51.011044+00:00",
      "balance": 6235.07,
      "equity": 6105.3
    },
    {
      "time": "2026-04-30T16:10:52.041320+00:00",
      "balance": 6235.07,
      "equity": 6114.75
    },
    {
      "time": "2026-04-30T16:10:53.066473+00:00",
      "balance": 6235.07,
      "equity": 6113.18
    },
    {
      "time": "2026-04-30T16:10:54.096354+00:00",
      "balance": 6235.07,
      "equity": 6091.26
    },
    {
      "time": "2026-04-30T16:10:55.127418+00:00",
      "balance": 6235.07,
      "equity": 6109.71
    },
    {
      "time": "2026-04-30T16:10:56.156604+00:00",
      "balance": 6235.07,
      "equity": 6097.38
    },
    {
      "time": "2026-04-30T16:10:57.183561+00:00",
      "balance": 6235.07,
      "equity": 6110.2
    },
    {
      "time": "2026-04-30T16:10:58.209281+00:00",
      "balance": 6235.07,
      "equity": 6111.56
    },
    {
      "time": "2026-04-30T16:10:59.239516+00:00",
      "balance": 6235.07,
      "equity": 6098.9
    },
    {
      "time": "2026-04-30T16:11:00.265881+00:00",
      "balance": 6235.07,
      "equity": 6095.1
    },
    {
      "time": "2026-04-30T16:11:01.296817+00:00",
      "balance": 6235.07,
      "equity": 6093.67
    },
    {
      "time": "2026-04-30T16:11:02.328684+00:00",
      "balance": 6235.07,
      "equity": 6090.18
    },
    {
      "time": "2026-04-30T16:11:03.364215+00:00",
      "balance": 6235.07,
      "equity": 6093.21
    },
    {
      "time": "2026-04-30T16:11:04.395176+00:00",
      "balance": 6235.07,
      "equity": 6094.61
    },
    {
      "time": "2026-04-30T16:11:21.546288+00:00",
      "balance": 6235.07,
      "equity": 6144.88
    },
    {
      "time": "2026-04-30T16:11:22.572997+00:00",
      "balance": 6235.07,
      "equity": 6145.88
    },
    {
      "time": "2026-04-30T16:11:23.599913+00:00",
      "balance": 6235.07,
      "equity": 6147.3
    },
    {
      "time": "2026-04-30T16:11:24.625521+00:00",
      "balance": 6235.07,
      "equity": 6143.06
    },
    {
      "time": "2026-04-30T16:11:25.657517+00:00",
      "balance": 6235.07,
      "equity": 6138.52
    },
    {
      "time": "2026-04-30T16:11:26.688404+00:00",
      "balance": 6235.07,
      "equity": 6123.61
    },
    {
      "time": "2026-04-30T16:11:27.721725+00:00",
      "balance": 6235.07,
      "equity": 6118.72
    },
    {
      "time": "2026-04-30T16:11:28.750032+00:00",
      "balance": 6235.07,
      "equity": 6100.24
    },
    {
      "time": "2026-04-30T16:11:29.776100+00:00",
      "balance": 6235.07,
      "equity": 6075.91
    },
    {
      "time": "2026-04-30T16:11:30.803108+00:00",
      "balance": 6235.07,
      "equity": 6087.9
    },
    {
      "time": "2026-04-30T16:11:31.830134+00:00",
      "balance": 6235.07,
      "equity": 6095.03
    },
    {
      "time": "2026-04-30T16:11:32.857560+00:00",
      "balance": 6235.07,
      "equity": 6088.58
    },
    {
      "time": "2026-04-30T16:11:33.885202+00:00",
      "balance": 6235.07,
      "equity": 6086.96
    },
    {
      "time": "2026-04-30T16:11:34.915687+00:00",
      "balance": 6235.07,
      "equity": 6087.48
    },
    {
      "time": "2026-04-30T16:11:35.948322+00:00",
      "balance": 6235.07,
      "equity": 6093.84
    },
    {
      "time": "2026-04-30T16:11:36.990261+00:00",
      "balance": 6235.07,
      "equity": 6093.77
    },
    {
      "time": "2026-04-30T16:11:38.033561+00:00",
      "balance": 6235.07,
      "equity": 6093.51
    },
    {
      "time": "2026-04-30T16:11:39.058530+00:00",
      "balance": 6235.07,
      "equity": 6091.48
    },
    {
      "time": "2026-04-30T16:11:40.088282+00:00",
      "balance": 6235.07,
      "equity": 6098.51
    },
    {
      "time": "2026-04-30T16:11:41.114635+00:00",
      "balance": 6235.07,
      "equity": 6096.69
    },
    {
      "time": "2026-04-30T16:11:42.140258+00:00",
      "balance": 6235.07,
      "equity": 6095.11
    },
    {
      "time": "2026-04-30T16:11:43.167403+00:00",
      "balance": 6235.07,
      "equity": 6095.1
    },
    {
      "time": "2026-04-30T16:11:44.194428+00:00",
      "balance": 6235.07,
      "equity": 6098.13
    },
    {
      "time": "2026-04-30T16:11:45.219769+00:00",
      "balance": 6235.07,
      "equity": 6084.17
    },
    {
      "time": "2026-04-30T16:11:46.246865+00:00",
      "balance": 6235.07,
      "equity": 6088.52
    },
    {
      "time": "2026-04-30T16:11:47.272092+00:00",
      "balance": 6235.07,
      "equity": 6091.44
    },
    {
      "time": "2026-04-30T16:11:48.297523+00:00",
      "balance": 6235.07,
      "equity": 6112.56
    },
    {
      "time": "2026-04-30T16:11:49.322944+00:00",
      "balance": 6235.07,
      "equity": 6110.75
    },
    {
      "time": "2026-04-30T16:11:50.350551+00:00",
      "balance": 6235.07,
      "equity": 6103.77
    },
    {
      "time": "2026-04-30T16:11:51.375306+00:00",
      "balance": 6235.07,
      "equity": 6102.0
    },
    {
      "time": "2026-04-30T16:11:52.399256+00:00",
      "balance": 6235.07,
      "equity": 6103.88
    },
    {
      "time": "2026-04-30T16:11:53.423357+00:00",
      "balance": 6235.07,
      "equity": 6115.69
    },
    {
      "time": "2026-04-30T16:11:54.446176+00:00",
      "balance": 6235.07,
      "equity": 6122.12
    },
    {
      "time": "2026-04-30T16:11:55.471260+00:00",
      "balance": 6235.07,
      "equity": 6116.15
    },
    {
      "time": "2026-04-30T16:11:56.495516+00:00",
      "balance": 6235.07,
      "equity": 6114.62
    },
    {
      "time": "2026-04-30T16:11:57.522622+00:00",
      "balance": 6235.07,
      "equity": 6113.23
    },
    {
      "time": "2026-04-30T16:11:58.546835+00:00",
      "balance": 6235.07,
      "equity": 6119.18
    },
    {
      "time": "2026-04-30T16:11:59.573560+00:00",
      "balance": 6235.07,
      "equity": 6127.58
    },
    {
      "time": "2026-04-30T16:12:00.603427+00:00",
      "balance": 6235.07,
      "equity": 6210.34
    },
    {
      "time": "2026-04-30T16:12:01.627613+00:00",
      "balance": 6235.07,
      "equity": 6200.91
    },
    {
      "time": "2026-04-30T16:12:02.652829+00:00",
      "balance": 6235.07,
      "equity": 6206.39
    },
    {
      "time": "2026-04-30T16:12:03.675898+00:00",
      "balance": 6235.07,
      "equity": 6201.0
    },
    {
      "time": "2026-04-30T16:12:04.698905+00:00",
      "balance": 6235.07,
      "equity": 6204.84
    },
    {
      "time": "2026-04-30T16:12:05.724719+00:00",
      "balance": 6235.07,
      "equity": 6203.24
    },
    {
      "time": "2026-04-30T16:12:06.756167+00:00",
      "balance": 6235.07,
      "equity": 6199.97
    },
    {
      "time": "2026-04-30T16:12:07.781297+00:00",
      "balance": 6235.07,
      "equity": 6211.13
    },
    {
      "time": "2026-04-30T16:12:08.805047+00:00",
      "balance": 6235.07,
      "equity": 6219.44
    },
    {
      "time": "2026-04-30T16:12:09.828762+00:00",
      "balance": 6235.07,
      "equity": 6231.49
    },
    {
      "time": "2026-04-30T16:12:10.858377+00:00",
      "balance": 6235.07,
      "equity": 6235.2
    },
    {
      "time": "2026-04-30T16:12:11.881791+00:00",
      "balance": 6235.07,
      "equity": 6220.44
    },
    {
      "time": "2026-04-30T16:12:12.908318+00:00",
      "balance": 6235.07,
      "equity": 6165.23
    },
    {
      "time": "2026-04-30T16:12:13.932803+00:00",
      "balance": 6235.07,
      "equity": 6175.91
    },
    {
      "time": "2026-04-30T16:12:14.959261+00:00",
      "balance": 6235.07,
      "equity": 6185.2
    },
    {
      "time": "2026-04-30T16:12:15.986952+00:00",
      "balance": 6235.07,
      "equity": 6200.29
    },
    {
      "time": "2026-04-30T16:12:17.014491+00:00",
      "balance": 6235.07,
      "equity": 6203.96
    },
    {
      "time": "2026-04-30T16:12:18.042059+00:00",
      "balance": 6235.07,
      "equity": 6203.27
    },
    {
      "time": "2026-04-30T16:12:19.069836+00:00",
      "balance": 6235.07,
      "equity": 6197.02
    },
    {
      "time": "2026-04-30T16:12:20.095338+00:00",
      "balance": 6235.07,
      "equity": 6180.25
    },
    {
      "time": "2026-04-30T16:12:21.122892+00:00",
      "balance": 6235.07,
      "equity": 6192.93
    },
    {
      "time": "2026-04-30T16:12:22.145213+00:00",
      "balance": 6235.07,
      "equity": 6195.06
    },
    {
      "time": "2026-04-30T16:12:23.170721+00:00",
      "balance": 6235.07,
      "equity": 6198.91
    },
    {
      "time": "2026-04-30T16:12:24.194468+00:00",
      "balance": 6235.07,
      "equity": 6200.49
    },
    {
      "time": "2026-04-30T16:12:25.219209+00:00",
      "balance": 6235.07,
      "equity": 6200.53
    },
    {
      "time": "2026-04-30T16:12:26.248155+00:00",
      "balance": 6235.07,
      "equity": 6199.33
    },
    {
      "time": "2026-04-30T16:12:27.283496+00:00",
      "balance": 6235.07,
      "equity": 6169.08
    },
    {
      "time": "2026-04-30T16:12:28.310139+00:00",
      "balance": 6235.07,
      "equity": 6183.31
    },
    {
      "time": "2026-04-30T16:12:29.337425+00:00",
      "balance": 6235.07,
      "equity": 6181.48
    },
    {
      "time": "2026-04-30T16:12:30.363498+00:00",
      "balance": 6235.07,
      "equity": 6183.29
    },
    {
      "time": "2026-04-30T16:12:31.387704+00:00",
      "balance": 6235.07,
      "equity": 6182.58
    },
    {
      "time": "2026-04-30T16:12:32.411556+00:00",
      "balance": 6235.07,
      "equity": 6209.47
    },
    {
      "time": "2026-04-30T16:12:33.437261+00:00",
      "balance": 6235.07,
      "equity": 6210.53
    },
    {
      "time": "2026-04-30T16:12:34.463802+00:00",
      "balance": 6235.07,
      "equity": 6209.58
    },
    {
      "time": "2026-04-30T16:12:35.501395+00:00",
      "balance": 6235.07,
      "equity": 6195.31
    },
    {
      "time": "2026-04-30T16:12:36.536464+00:00",
      "balance": 6235.07,
      "equity": 6207.33
    },
    {
      "time": "2026-04-30T16:12:37.561720+00:00",
      "balance": 6235.07,
      "equity": 6208.27
    },
    {
      "time": "2026-04-30T16:12:38.585417+00:00",
      "balance": 6235.07,
      "equity": 6208.37
    },
    {
      "time": "2026-04-30T16:12:39.611761+00:00",
      "balance": 6235.07,
      "equity": 6203.65
    },
    {
      "time": "2026-04-30T16:12:40.637182+00:00",
      "balance": 6235.07,
      "equity": 6213.91
    },
    {
      "time": "2026-04-30T16:12:41.664594+00:00",
      "balance": 6235.07,
      "equity": 6211.78
    },
    {
      "time": "2026-04-30T16:12:42.689382+00:00",
      "balance": 6235.07,
      "equity": 6211.16
    },
    {
      "time": "2026-04-30T16:12:43.717015+00:00",
      "balance": 6235.07,
      "equity": 6213.84
    },
    {
      "time": "2026-04-30T16:12:44.741381+00:00",
      "balance": 6235.07,
      "equity": 6204.92
    },
    {
      "time": "2026-04-30T16:12:45.765389+00:00",
      "balance": 6235.07,
      "equity": 6217.79
    },
    {
      "time": "2026-04-30T16:12:46.789273+00:00",
      "balance": 6235.07,
      "equity": 6219.09
    },
    {
      "time": "2026-04-30T16:12:47.813551+00:00",
      "balance": 6235.07,
      "equity": 6217.44
    },
    {
      "time": "2026-04-30T16:12:48.840648+00:00",
      "balance": 6235.07,
      "equity": 6215.7
    },
    {
      "time": "2026-04-30T16:12:49.904684+00:00",
      "balance": 6235.07,
      "equity": 6209.59
    },
    {
      "time": "2026-04-30T16:12:50.931585+00:00",
      "balance": 6235.07,
      "equity": 6218.2
    },
    {
      "time": "2026-04-30T16:12:51.954879+00:00",
      "balance": 6235.07,
      "equity": 6209.68
    },
    {
      "time": "2026-04-30T16:12:52.979417+00:00",
      "balance": 6235.07,
      "equity": 6209.22
    },
    {
      "time": "2026-04-30T16:12:54.006351+00:00",
      "balance": 6235.07,
      "equity": 6216.63
    },
    {
      "time": "2026-04-30T16:12:55.031755+00:00",
      "balance": 6235.07,
      "equity": 6224.67
    },
    {
      "time": "2026-04-30T16:12:56.058355+00:00",
      "balance": 6235.07,
      "equity": 6213.95
    },
    {
      "time": "2026-04-30T16:12:57.082644+00:00",
      "balance": 6235.07,
      "equity": 6222.23
    },
    {
      "time": "2026-04-30T16:12:58.107361+00:00",
      "balance": 6235.07,
      "equity": 6222.26
    },
    {
      "time": "2026-04-30T16:12:59.131124+00:00",
      "balance": 6235.07,
      "equity": 6223.31
    },
    {
      "time": "2026-04-30T16:13:00.156978+00:00",
      "balance": 6235.07,
      "equity": 6228.47
    },
    {
      "time": "2026-04-30T16:13:01.183350+00:00",
      "balance": 6235.07,
      "equity": 6250.93
    },
    {
      "time": "2026-04-30T16:13:02.209815+00:00",
      "balance": 6235.07,
      "equity": 6249.83
    },
    {
      "time": "2026-04-30T16:13:03.234502+00:00",
      "balance": 6235.07,
      "equity": 6261.45
    },
    {
      "time": "2026-04-30T16:13:04.258998+00:00",
      "balance": 6235.07,
      "equity": 6269.15
    },
    {
      "time": "2026-04-30T16:13:05.285716+00:00",
      "balance": 6235.07,
      "equity": 6276.13
    },
    {
      "time": "2026-04-30T16:13:06.312442+00:00",
      "balance": 6235.07,
      "equity": 6274.89
    },
    {
      "time": "2026-04-30T16:13:07.343314+00:00",
      "balance": 6235.07,
      "equity": 6275.42
    },
    {
      "time": "2026-04-30T16:13:08.371456+00:00",
      "balance": 6235.07,
      "equity": 6270.53
    },
    {
      "time": "2026-04-30T16:13:09.395809+00:00",
      "balance": 6235.07,
      "equity": 6272.11
    },
    {
      "time": "2026-04-30T16:13:10.420153+00:00",
      "balance": 6235.07,
      "equity": 6278.91
    },
    {
      "time": "2026-04-30T16:13:11.446297+00:00",
      "balance": 6235.07,
      "equity": 6276.86
    },
    {
      "time": "2026-04-30T16:13:12.472512+00:00",
      "balance": 6235.07,
      "equity": 6254.8
    },
    {
      "time": "2026-04-30T16:13:13.498198+00:00",
      "balance": 6235.07,
      "equity": 6253.63
    },
    {
      "time": "2026-04-30T16:13:14.524214+00:00",
      "balance": 6235.07,
      "equity": 6255.1
    },
    {
      "time": "2026-04-30T16:13:15.550825+00:00",
      "balance": 6235.07,
      "equity": 6285.44
    },
    {
      "time": "2026-04-30T16:13:16.579834+00:00",
      "balance": 6235.07,
      "equity": 6289.93
    },
    {
      "time": "2026-04-30T16:13:17.606277+00:00",
      "balance": 6235.07,
      "equity": 6286.7
    },
    {
      "time": "2026-04-30T16:13:18.631245+00:00",
      "balance": 6235.07,
      "equity": 6294.81
    },
    {
      "time": "2026-04-30T16:13:19.656924+00:00",
      "balance": 6235.07,
      "equity": 6285.75
    },
    {
      "time": "2026-04-30T16:13:20.682963+00:00",
      "balance": 6235.07,
      "equity": 6280.91
    },
    {
      "time": "2026-04-30T16:13:21.716774+00:00",
      "balance": 6235.07,
      "equity": 6293.05
    },
    {
      "time": "2026-04-30T16:13:22.747205+00:00",
      "balance": 6235.07,
      "equity": 6301.74
    },
    {
      "time": "2026-04-30T16:13:23.772317+00:00",
      "balance": 6235.07,
      "equity": 6297.42
    },
    {
      "time": "2026-04-30T16:13:24.794833+00:00",
      "balance": 6235.07,
      "equity": 6297.45
    },
    {
      "time": "2026-04-30T16:13:25.827265+00:00",
      "balance": 6235.07,
      "equity": 6297.93
    },
    {
      "time": "2026-04-30T16:13:26.857484+00:00",
      "balance": 6235.07,
      "equity": 6301.72
    },
    {
      "time": "2026-04-30T16:13:27.885507+00:00",
      "balance": 6235.07,
      "equity": 6304.95
    },
    {
      "time": "2026-04-30T16:13:28.910431+00:00",
      "balance": 6235.07,
      "equity": 6313.25
    },
    {
      "time": "2026-04-30T16:13:29.935696+00:00",
      "balance": 6235.07,
      "equity": 6313.25
    },
    {
      "time": "2026-04-30T16:13:30.961004+00:00",
      "balance": 6235.07,
      "equity": 6309.77
    },
    {
      "time": "2026-04-30T16:13:31.987338+00:00",
      "balance": 6235.07,
      "equity": 6306.84
    },
    {
      "time": "2026-04-30T16:13:33.015504+00:00",
      "balance": 6235.07,
      "equity": 6281.64
    },
    {
      "time": "2026-04-30T16:13:34.043583+00:00",
      "balance": 6235.07,
      "equity": 6285.03
    },
    {
      "time": "2026-04-30T16:13:35.069743+00:00",
      "balance": 6235.07,
      "equity": 6294.33
    },
    {
      "time": "2026-04-30T16:13:36.095165+00:00",
      "balance": 6235.07,
      "equity": 6302.75
    },
    {
      "time": "2026-04-30T16:13:37.119539+00:00",
      "balance": 6235.07,
      "equity": 6309.44
    },
    {
      "time": "2026-04-30T16:13:38.149573+00:00",
      "balance": 6235.07,
      "equity": 6306.39
    },
    {
      "time": "2026-04-30T16:13:39.175378+00:00",
      "balance": 6235.07,
      "equity": 6308.05
    },
    {
      "time": "2026-04-30T16:13:40.201857+00:00",
      "balance": 6235.07,
      "equity": 6309.44
    },
    {
      "time": "2026-04-30T16:13:41.227544+00:00",
      "balance": 6235.07,
      "equity": 6336.19
    },
    {
      "time": "2026-04-30T16:13:42.252597+00:00",
      "balance": 6235.07,
      "equity": 6376.94
    },
    {
      "time": "2026-04-30T16:13:43.277352+00:00",
      "balance": 6235.07,
      "equity": 6370.26
    },
    {
      "time": "2026-04-30T16:13:44.302075+00:00",
      "balance": 6235.07,
      "equity": 6386.21
    },
    {
      "time": "2026-04-30T16:13:45.327754+00:00",
      "balance": 6235.07,
      "equity": 6380.78
    },
    {
      "time": "2026-04-30T16:13:46.356175+00:00",
      "balance": 6235.07,
      "equity": 6381.63
    },
    {
      "time": "2026-04-30T16:13:47.381795+00:00",
      "balance": 6235.07,
      "equity": 6371.46
    },
    {
      "time": "2026-04-30T16:13:48.406398+00:00",
      "balance": 6235.07,
      "equity": 6362.41
    },
    {
      "time": "2026-04-30T16:13:49.432792+00:00",
      "balance": 6235.07,
      "equity": 6364.31
    },
    {
      "time": "2026-04-30T16:13:50.458272+00:00",
      "balance": 6235.07,
      "equity": 6339.18
    },
    {
      "time": "2026-04-30T16:13:51.484755+00:00",
      "balance": 6235.07,
      "equity": 6321.88
    },
    {
      "time": "2026-04-30T16:13:52.511002+00:00",
      "balance": 6235.07,
      "equity": 6327.56
    },
    {
      "time": "2026-04-30T16:13:53.535088+00:00",
      "balance": 6235.07,
      "equity": 6327.2
    },
    {
      "time": "2026-04-30T16:13:54.563959+00:00",
      "balance": 6235.07,
      "equity": 6335.68
    },
    {
      "time": "2026-04-30T16:13:55.590395+00:00",
      "balance": 6235.07,
      "equity": 6341.51
    },
    {
      "time": "2026-04-30T16:13:56.616416+00:00",
      "balance": 6235.07,
      "equity": 6343.03
    },
    {
      "time": "2026-04-30T16:13:57.641408+00:00",
      "balance": 6235.07,
      "equity": 6340.74
    },
    {
      "time": "2026-04-30T16:13:58.666515+00:00",
      "balance": 6235.07,
      "equity": 6351.76
    },
    {
      "time": "2026-04-30T16:13:59.693893+00:00",
      "balance": 6235.07,
      "equity": 6349.89
    },
    {
      "time": "2026-04-30T16:14:00.725049+00:00",
      "balance": 6235.07,
      "equity": 6353.53
    },
    {
      "time": "2026-04-30T16:14:01.751254+00:00",
      "balance": 6235.07,
      "equity": 6374.6
    },
    {
      "time": "2026-04-30T16:14:02.776437+00:00",
      "balance": 6235.07,
      "equity": 6359.53
    },
    {
      "time": "2026-04-30T16:14:03.801243+00:00",
      "balance": 6235.07,
      "equity": 6374.29
    },
    {
      "time": "2026-04-30T16:14:04.826368+00:00",
      "balance": 6235.07,
      "equity": 6387.52
    },
    {
      "time": "2026-04-30T16:14:05.855597+00:00",
      "balance": 6235.07,
      "equity": 6382.27
    },
    {
      "time": "2026-04-30T16:14:06.880183+00:00",
      "balance": 6235.07,
      "equity": 6385.49
    },
    {
      "time": "2026-04-30T16:14:07.906192+00:00",
      "balance": 6235.07,
      "equity": 6386.51
    },
    {
      "time": "2026-04-30T16:14:08.932230+00:00",
      "balance": 6235.07,
      "equity": 6385.94
    },
    {
      "time": "2026-04-30T16:14:09.958701+00:00",
      "balance": 6235.07,
      "equity": 6380.55
    },
    {
      "time": "2026-04-30T16:14:10.983713+00:00",
      "balance": 6235.07,
      "equity": 6380.86
    },
    {
      "time": "2026-04-30T16:14:12.012646+00:00",
      "balance": 6235.07,
      "equity": 6387.46
    },
    {
      "time": "2026-04-30T16:14:13.037756+00:00",
      "balance": 6235.07,
      "equity": 6389.22
    },
    {
      "time": "2026-04-30T16:14:14.062595+00:00",
      "balance": 6235.07,
      "equity": 6365.29
    },
    {
      "time": "2026-04-30T16:14:15.111537+00:00",
      "balance": 6235.07,
      "equity": 6380.24
    },
    {
      "time": "2026-04-30T16:14:16.133286+00:00",
      "balance": 6235.07,
      "equity": 6381.88
    },
    {
      "time": "2026-04-30T16:14:17.154417+00:00",
      "balance": 6235.07,
      "equity": 6381.31
    },
    {
      "time": "2026-04-30T16:14:18.175261+00:00",
      "balance": 6235.07,
      "equity": 6379.33
    },
    {
      "time": "2026-04-30T16:14:19.196515+00:00",
      "balance": 6235.07,
      "equity": 6377.81
    },
    {
      "time": "2026-04-30T16:14:20.217747+00:00",
      "balance": 6235.07,
      "equity": 6370.25
    },
    {
      "time": "2026-04-30T16:14:21.239970+00:00",
      "balance": 6235.07,
      "equity": 6356.1
    },
    {
      "time": "2026-04-30T16:14:22.262519+00:00",
      "balance": 6235.07,
      "equity": 6357.04
    },
    {
      "time": "2026-04-30T16:14:23.285797+00:00",
      "balance": 6235.07,
      "equity": 6345.86
    },
    {
      "time": "2026-04-30T16:14:24.307700+00:00",
      "balance": 6235.07,
      "equity": 6340.41
    },
    {
      "time": "2026-04-30T16:14:25.328477+00:00",
      "balance": 6235.07,
      "equity": 6341.46
    },
    {
      "time": "2026-04-30T16:14:26.355374+00:00",
      "balance": 6235.07,
      "equity": 6340.83
    },
    {
      "time": "2026-04-30T16:14:27.376362+00:00",
      "balance": 6235.07,
      "equity": 6349.79
    },
    {
      "time": "2026-04-30T16:14:28.398178+00:00",
      "balance": 6235.07,
      "equity": 6351.1
    },
    {
      "time": "2026-04-30T16:14:29.522592+00:00",
      "balance": 6235.07,
      "equity": 6341.44
    },
    {
      "time": "2026-04-30T16:14:30.544130+00:00",
      "balance": 6235.07,
      "equity": 6328.09
    },
    {
      "time": "2026-04-30T16:14:31.569186+00:00",
      "balance": 6235.07,
      "equity": 6323.82
    },
    {
      "time": "2026-04-30T16:14:32.592306+00:00",
      "balance": 6235.07,
      "equity": 6293.0
    },
    {
      "time": "2026-04-30T16:14:33.617340+00:00",
      "balance": 6235.07,
      "equity": 6298.13
    },
    {
      "time": "2026-04-30T16:14:34.638543+00:00",
      "balance": 6235.07,
      "equity": 6291.24
    },
    {
      "time": "2026-04-30T16:14:35.661866+00:00",
      "balance": 6235.07,
      "equity": 6292.89
    },
    {
      "time": "2026-04-30T16:14:36.686018+00:00",
      "balance": 6235.07,
      "equity": 6291.14
    },
    {
      "time": "2026-04-30T16:14:37.707111+00:00",
      "balance": 6235.07,
      "equity": 6275.34
    },
    {
      "time": "2026-04-30T16:14:38.729437+00:00",
      "balance": 6235.07,
      "equity": 6294.07
    },
    {
      "time": "2026-04-30T16:14:39.751221+00:00",
      "balance": 6235.07,
      "equity": 6298.84
    },
    {
      "time": "2026-04-30T16:14:40.775232+00:00",
      "balance": 6235.07,
      "equity": 6307.86
    },
    {
      "time": "2026-04-30T16:14:41.806223+00:00",
      "balance": 6235.07,
      "equity": 6315.65
    },
    {
      "time": "2026-04-30T16:14:42.830208+00:00",
      "balance": 6235.07,
      "equity": 6313.86
    },
    {
      "time": "2026-04-30T16:14:43.854396+00:00",
      "balance": 6235.07,
      "equity": 6301.02
    },
    {
      "time": "2026-04-30T16:14:44.876557+00:00",
      "balance": 6235.07,
      "equity": 6309.1
    },
    {
      "time": "2026-04-30T16:14:45.899030+00:00",
      "balance": 6235.07,
      "equity": 6334.43
    },
    {
      "time": "2026-04-30T16:14:46.919464+00:00",
      "balance": 6235.07,
      "equity": 6341.79
    },
    {
      "time": "2026-04-30T16:14:47.941254+00:00",
      "balance": 6235.07,
      "equity": 6329.22
    },
    {
      "time": "2026-04-30T16:14:48.963944+00:00",
      "balance": 6235.07,
      "equity": 6328.92
    },
    {
      "time": "2026-04-30T16:14:49.986206+00:00",
      "balance": 6235.07,
      "equity": 6328.16
    },
    {
      "time": "2026-04-30T16:14:51.007768+00:00",
      "balance": 6235.07,
      "equity": 6315.54
    },
    {
      "time": "2026-04-30T16:14:52.029580+00:00",
      "balance": 6235.07,
      "equity": 6310.89
    },
    {
      "time": "2026-04-30T16:14:53.056612+00:00",
      "balance": 6235.07,
      "equity": 6319.66
    },
    {
      "time": "2026-04-30T16:14:54.079616+00:00",
      "balance": 6235.07,
      "equity": 6329.94
    },
    {
      "time": "2026-04-30T16:14:55.103063+00:00",
      "balance": 6235.07,
      "equity": 6331.74
    },
    {
      "time": "2026-04-30T16:14:56.125578+00:00",
      "balance": 6235.07,
      "equity": 6346.8
    },
    {
      "time": "2026-04-30T16:14:57.146742+00:00",
      "balance": 6235.07,
      "equity": 6344.82
    },
    {
      "time": "2026-04-30T16:14:58.168085+00:00",
      "balance": 6235.07,
      "equity": 6342.33
    },
    {
      "time": "2026-04-30T16:14:59.189494+00:00",
      "balance": 6235.07,
      "equity": 6340.4
    },
    {
      "time": "2026-04-30T16:15:00.213185+00:00",
      "balance": 6235.07,
      "equity": 6338.85
    },
    {
      "time": "2026-04-30T16:15:01.234045+00:00",
      "balance": 6235.07,
      "equity": 6355.0
    },
    {
      "time": "2026-04-30T16:15:02.260598+00:00",
      "balance": 6235.07,
      "equity": 6349.16
    },
    {
      "time": "2026-04-30T16:15:03.281905+00:00",
      "balance": 6235.07,
      "equity": 6312.29
    },
    {
      "time": "2026-04-30T16:15:04.306653+00:00",
      "balance": 6235.07,
      "equity": 6308.4
    },
    {
      "time": "2026-04-30T16:15:05.327380+00:00",
      "balance": 6235.07,
      "equity": 6306.7
    },
    {
      "time": "2026-04-30T16:15:06.354686+00:00",
      "balance": 6235.07,
      "equity": 6290.67
    },
    {
      "time": "2026-04-30T16:15:07.378668+00:00",
      "balance": 6235.07,
      "equity": 6296.91
    },
    {
      "time": "2026-04-30T16:15:08.407817+00:00",
      "balance": 6235.07,
      "equity": 6296.17
    },
    {
      "time": "2026-04-30T16:15:09.429453+00:00",
      "balance": 6235.07,
      "equity": 6288.21
    },
    {
      "time": "2026-04-30T16:15:10.452941+00:00",
      "balance": 6235.07,
      "equity": 6288.48
    },
    {
      "time": "2026-04-30T16:15:11.478238+00:00",
      "balance": 6235.07,
      "equity": 6296.23
    },
    {
      "time": "2026-04-30T16:15:12.501160+00:00",
      "balance": 6235.07,
      "equity": 6285.51
    },
    {
      "time": "2026-04-30T16:15:13.525207+00:00",
      "balance": 6235.07,
      "equity": 6285.65
    },
    {
      "time": "2026-04-30T16:15:14.547405+00:00",
      "balance": 6235.07,
      "equity": 6288.68
    },
    {
      "time": "2026-04-30T16:15:15.570866+00:00",
      "balance": 6235.07,
      "equity": 6279.84
    },
    {
      "time": "2026-04-30T16:15:16.594034+00:00",
      "balance": 6235.07,
      "equity": 6271.18
    },
    {
      "time": "2026-04-30T16:15:17.619387+00:00",
      "balance": 6235.07,
      "equity": 6271.48
    },
    {
      "time": "2026-04-30T16:15:18.642500+00:00",
      "balance": 6235.07,
      "equity": 6284.33
    },
    {
      "time": "2026-04-30T16:15:19.665980+00:00",
      "balance": 6235.07,
      "equity": 6304.93
    },
    {
      "time": "2026-04-30T16:15:20.688805+00:00",
      "balance": 6235.07,
      "equity": 6301.34
    },
    {
      "time": "2026-04-30T16:15:21.713076+00:00",
      "balance": 6235.07,
      "equity": 6308.67
    },
    {
      "time": "2026-04-30T16:15:22.734903+00:00",
      "balance": 6235.07,
      "equity": 6306.44
    },
    {
      "time": "2026-04-30T16:15:23.757761+00:00",
      "balance": 6235.07,
      "equity": 6311.14
    },
    {
      "time": "2026-04-30T16:15:24.779817+00:00",
      "balance": 6235.07,
      "equity": 6306.44
    },
    {
      "time": "2026-04-30T16:15:25.809484+00:00",
      "balance": 6235.07,
      "equity": 6311.62
    },
    {
      "time": "2026-04-30T16:15:26.837829+00:00",
      "balance": 6235.07,
      "equity": 6306.62
    },
    {
      "time": "2026-04-30T16:15:27.863107+00:00",
      "balance": 6235.07,
      "equity": 6314.45
    },
    {
      "time": "2026-04-30T16:15:28.886132+00:00",
      "balance": 6235.07,
      "equity": 6309.62
    },
    {
      "time": "2026-04-30T16:15:29.908176+00:00",
      "balance": 6235.07,
      "equity": 6315.74
    },
    {
      "time": "2026-04-30T16:15:30.930517+00:00",
      "balance": 6235.07,
      "equity": 6315.41
    },
    {
      "time": "2026-04-30T16:15:31.953911+00:00",
      "balance": 6235.07,
      "equity": 6312.95
    },
    {
      "time": "2026-04-30T16:15:32.976483+00:00",
      "balance": 6235.07,
      "equity": 6313.08
    },
    {
      "time": "2026-04-30T16:15:34.000887+00:00",
      "balance": 6235.07,
      "equity": 6309.78
    },
    {
      "time": "2026-04-30T16:15:35.023215+00:00",
      "balance": 6235.07,
      "equity": 6313.92
    },
    {
      "time": "2026-04-30T16:15:36.044839+00:00",
      "balance": 6235.07,
      "equity": 6314.38
    },
    {
      "time": "2026-04-30T16:15:37.067314+00:00",
      "balance": 6235.07,
      "equity": 6321.55
    },
    {
      "time": "2026-04-30T16:15:38.090012+00:00",
      "balance": 6235.07,
      "equity": 6317.13
    },
    {
      "time": "2026-04-30T16:15:39.114648+00:00",
      "balance": 6235.07,
      "equity": 6303.25
    },
    {
      "time": "2026-04-30T16:15:40.135864+00:00",
      "balance": 6235.07,
      "equity": 6309.31
    },
    {
      "time": "2026-04-30T16:15:41.158813+00:00",
      "balance": 6235.07,
      "equity": 6298.26
    },
    {
      "time": "2026-04-30T16:15:42.180249+00:00",
      "balance": 6235.07,
      "equity": 6300.01
    },
    {
      "time": "2026-04-30T16:15:43.203495+00:00",
      "balance": 6235.07,
      "equity": 6302.04
    },
    {
      "time": "2026-04-30T16:15:44.227332+00:00",
      "balance": 6235.07,
      "equity": 6303.62
    },
    {
      "time": "2026-04-30T16:15:45.252579+00:00",
      "balance": 6235.07,
      "equity": 6299.68
    },
    {
      "time": "2026-04-30T16:15:46.274503+00:00",
      "balance": 6235.07,
      "equity": 6289.34
    },
    {
      "time": "2026-04-30T16:15:47.296738+00:00",
      "balance": 6235.07,
      "equity": 6284.51
    },
    {
      "time": "2026-04-30T16:15:48.319091+00:00",
      "balance": 6235.07,
      "equity": 6285.16
    },
    {
      "time": "2026-04-30T16:15:49.346292+00:00",
      "balance": 6235.07,
      "equity": 6282.84
    },
    {
      "time": "2026-04-30T16:15:50.369375+00:00",
      "balance": 6235.07,
      "equity": 6274.35
    },
    {
      "time": "2026-04-30T16:15:51.394822+00:00",
      "balance": 6235.07,
      "equity": 6264.56
    },
    {
      "time": "2026-04-30T16:15:52.415857+00:00",
      "balance": 6235.07,
      "equity": 6268.82
    },
    {
      "time": "2026-04-30T16:15:53.438840+00:00",
      "balance": 6235.07,
      "equity": 6268.89
    },
    {
      "time": "2026-04-30T16:15:54.460595+00:00",
      "balance": 6235.07,
      "equity": 6271.41
    },
    {
      "time": "2026-04-30T16:15:55.482886+00:00",
      "balance": 6235.07,
      "equity": 6268.47
    },
    {
      "time": "2026-04-30T16:15:56.506291+00:00",
      "balance": 6235.07,
      "equity": 6283.9
    },
    {
      "time": "2026-04-30T16:15:57.528159+00:00",
      "balance": 6235.07,
      "equity": 6270.61
    },
    {
      "time": "2026-04-30T16:15:58.549938+00:00",
      "balance": 6235.07,
      "equity": 6269.87
    },
    {
      "time": "2026-04-30T16:15:59.574029+00:00",
      "balance": 6235.07,
      "equity": 6272.78
    },
    {
      "time": "2026-04-30T16:16:00.604464+00:00",
      "balance": 6235.07,
      "equity": 6197.06
    },
    {
      "time": "2026-04-30T16:16:01.628131+00:00",
      "balance": 6235.07,
      "equity": 6208.53
    },
    {
      "time": "2026-04-30T16:16:02.649539+00:00",
      "balance": 6235.07,
      "equity": 6185.07
    },
    {
      "time": "2026-04-30T16:16:03.671184+00:00",
      "balance": 6235.07,
      "equity": 6196.79
    },
    {
      "time": "2026-04-30T16:16:04.696956+00:00",
      "balance": 6235.07,
      "equity": 6195.3
    },
    {
      "time": "2026-04-30T16:16:05.726529+00:00",
      "balance": 6235.07,
      "equity": 6185.84
    },
    {
      "time": "2026-04-30T16:16:06.751923+00:00",
      "balance": 6235.07,
      "equity": 6186.8
    },
    {
      "time": "2026-04-30T16:16:07.775586+00:00",
      "balance": 6235.07,
      "equity": 6180.32
    },
    {
      "time": "2026-04-30T16:16:08.797350+00:00",
      "balance": 6235.07,
      "equity": 6177.17
    },
    {
      "time": "2026-04-30T16:16:09.819469+00:00",
      "balance": 6235.07,
      "equity": 6178.57
    },
    {
      "time": "2026-04-30T16:16:10.841968+00:00",
      "balance": 6235.07,
      "equity": 6168.04
    },
    {
      "time": "2026-04-30T16:16:11.866569+00:00",
      "balance": 6235.07,
      "equity": 6166.68
    },
    {
      "time": "2026-04-30T16:16:12.892318+00:00",
      "balance": 6235.07,
      "equity": 6169.75
    },
    {
      "time": "2026-04-30T16:16:13.914709+00:00",
      "balance": 6235.07,
      "equity": 6152.95
    },
    {
      "time": "2026-04-30T16:16:14.935859+00:00",
      "balance": 6235.07,
      "equity": 6164.13
    },
    {
      "time": "2026-04-30T16:16:15.960504+00:00",
      "balance": 6235.07,
      "equity": 6167.41
    },
    {
      "time": "2026-04-30T16:16:16.982744+00:00",
      "balance": 6235.07,
      "equity": 6175.42
    },
    {
      "time": "2026-04-30T16:16:18.008599+00:00",
      "balance": 6235.07,
      "equity": 6162.26
    },
    {
      "time": "2026-04-30T16:16:19.031842+00:00",
      "balance": 6235.07,
      "equity": 6164.98
    },
    {
      "time": "2026-04-30T16:16:20.067714+00:00",
      "balance": 6235.07,
      "equity": 6164.65
    },
    {
      "time": "2026-04-30T16:16:21.091554+00:00",
      "balance": 6235.07,
      "equity": 6171.66
    },
    {
      "time": "2026-04-30T16:16:22.113942+00:00",
      "balance": 6235.07,
      "equity": 6167.18
    },
    {
      "time": "2026-04-30T16:16:23.138413+00:00",
      "balance": 6235.07,
      "equity": 6167.72
    },
    {
      "time": "2026-04-30T16:16:24.163031+00:00",
      "balance": 6235.07,
      "equity": 6166.95
    },
    {
      "time": "2026-04-30T16:16:25.184866+00:00",
      "balance": 6235.07,
      "equity": 6159.8
    },
    {
      "time": "2026-04-30T16:16:26.213387+00:00",
      "balance": 6235.07,
      "equity": 6165.68
    },
    {
      "time": "2026-04-30T16:16:27.241202+00:00",
      "balance": 6235.07,
      "equity": 6142.64
    },
    {
      "time": "2026-04-30T16:16:28.261925+00:00",
      "balance": 6235.07,
      "equity": 6134.38
    },
    {
      "time": "2026-04-30T16:16:29.286417+00:00",
      "balance": 6235.07,
      "equity": 6137.6
    },
    {
      "time": "2026-04-30T16:16:30.308670+00:00",
      "balance": 6235.07,
      "equity": 6115.89
    },
    {
      "time": "2026-04-30T16:16:31.335025+00:00",
      "balance": 6235.07,
      "equity": 6119.81
    },
    {
      "time": "2026-04-30T16:16:32.373509+00:00",
      "balance": 6235.07,
      "equity": 6125.74
    },
    {
      "time": "2026-04-30T16:16:33.405562+00:00",
      "balance": 6235.07,
      "equity": 6122.62
    },
    {
      "time": "2026-04-30T16:16:34.435628+00:00",
      "balance": 6235.07,
      "equity": 6145.47
    },
    {
      "time": "2026-04-30T16:16:35.460765+00:00",
      "balance": 6235.07,
      "equity": 6141.65
    },
    {
      "time": "2026-04-30T16:16:36.494243+00:00",
      "balance": 6235.07,
      "equity": 6140.65
    },
    {
      "time": "2026-04-30T16:16:37.528405+00:00",
      "balance": 6235.07,
      "equity": 6136.01
    },
    {
      "time": "2026-04-30T16:16:38.551140+00:00",
      "balance": 6235.07,
      "equity": 6141.74
    },
    {
      "time": "2026-04-30T16:16:39.575574+00:00",
      "balance": 6235.07,
      "equity": 6142.58
    },
    {
      "time": "2026-04-30T16:16:40.598696+00:00",
      "balance": 6235.07,
      "equity": 6143.02
    },
    {
      "time": "2026-04-30T16:16:41.621943+00:00",
      "balance": 6235.07,
      "equity": 6141.81
    },
    {
      "time": "2026-04-30T16:16:42.645943+00:00",
      "balance": 6235.07,
      "equity": 6151.45
    },
    {
      "time": "2026-04-30T16:16:43.673958+00:00",
      "balance": 6235.07,
      "equity": 6160.87
    },
    {
      "time": "2026-04-30T16:16:44.701828+00:00",
      "balance": 6235.07,
      "equity": 6175.18
    },
    {
      "time": "2026-04-30T16:16:45.731109+00:00",
      "balance": 6235.07,
      "equity": 6175.11
    },
    {
      "time": "2026-04-30T16:16:46.752703+00:00",
      "balance": 6235.07,
      "equity": 6183.61
    },
    {
      "time": "2026-04-30T16:16:47.778050+00:00",
      "balance": 6235.07,
      "equity": 6171.36
    },
    {
      "time": "2026-04-30T16:16:48.806843+00:00",
      "balance": 6235.07,
      "equity": 6171.45
    },
    {
      "time": "2026-04-30T16:16:49.830295+00:00",
      "balance": 6235.07,
      "equity": 6163.75
    },
    {
      "time": "2026-04-30T16:16:50.853649+00:00",
      "balance": 6235.07,
      "equity": 6175.91
    },
    {
      "time": "2026-04-30T16:16:51.879058+00:00",
      "balance": 6235.07,
      "equity": 6162.26
    },
    {
      "time": "2026-04-30T16:16:52.903481+00:00",
      "balance": 6235.07,
      "equity": 6157.15
    },
    {
      "time": "2026-04-30T16:16:53.941743+00:00",
      "balance": 6235.07,
      "equity": 6156.14
    },
    {
      "time": "2026-04-30T16:16:54.968515+00:00",
      "balance": 6235.07,
      "equity": 6157.98
    },
    {
      "time": "2026-04-30T16:16:55.991893+00:00",
      "balance": 6235.07,
      "equity": 6133.87
    },
    {
      "time": "2026-04-30T16:16:57.016479+00:00",
      "balance": 6235.07,
      "equity": 6136.0
    },
    {
      "time": "2026-04-30T16:16:59.315614+00:00",
      "balance": 6235.07,
      "equity": 6129.42
    },
    {
      "time": "2026-04-30T16:17:00.344375+00:00",
      "balance": 6235.07,
      "equity": 6126.93
    },
    {
      "time": "2026-04-30T16:17:01.370984+00:00",
      "balance": 6235.07,
      "equity": 6134.24
    },
    {
      "time": "2026-04-30T16:17:02.397213+00:00",
      "balance": 6235.07,
      "equity": 6127.93
    },
    {
      "time": "2026-04-30T16:17:03.421416+00:00",
      "balance": 6235.07,
      "equity": 6105.75
    },
    {
      "time": "2026-04-30T16:17:04.447734+00:00",
      "balance": 6235.07,
      "equity": 6108.37
    },
    {
      "time": "2026-04-30T16:17:05.473368+00:00",
      "balance": 6235.07,
      "equity": 6106.0
    },
    {
      "time": "2026-04-30T16:17:06.501555+00:00",
      "balance": 6235.07,
      "equity": 6099.57
    },
    {
      "time": "2026-04-30T16:17:07.530387+00:00",
      "balance": 6235.07,
      "equity": 6107.79
    },
    {
      "time": "2026-04-30T16:17:08.554357+00:00",
      "balance": 6235.07,
      "equity": 6097.71
    },
    {
      "time": "2026-04-30T16:17:09.578449+00:00",
      "balance": 6235.07,
      "equity": 6103.51
    },
    {
      "time": "2026-04-30T16:17:10.602642+00:00",
      "balance": 6235.07,
      "equity": 6099.02
    },
    {
      "time": "2026-04-30T16:17:11.625872+00:00",
      "balance": 6235.07,
      "equity": 6099.79
    },
    {
      "time": "2026-04-30T16:17:12.651243+00:00",
      "balance": 6235.07,
      "equity": 6114.93
    },
    {
      "time": "2026-04-30T16:17:13.673922+00:00",
      "balance": 6235.07,
      "equity": 6112.09
    },
    {
      "time": "2026-04-30T16:17:14.698738+00:00",
      "balance": 6235.07,
      "equity": 6132.32
    },
    {
      "time": "2026-04-30T16:17:15.722951+00:00",
      "balance": 6235.07,
      "equity": 6126.38
    },
    {
      "time": "2026-04-30T16:17:16.749738+00:00",
      "balance": 6235.07,
      "equity": 6132.55
    },
    {
      "time": "2026-04-30T16:17:17.772298+00:00",
      "balance": 6235.07,
      "equity": 6125.7
    },
    {
      "time": "2026-04-30T16:17:18.796311+00:00",
      "balance": 6235.07,
      "equity": 6116.21
    },
    {
      "time": "2026-04-30T16:17:19.820215+00:00",
      "balance": 6235.07,
      "equity": 6119.35
    },
    {
      "time": "2026-04-30T16:17:20.845257+00:00",
      "balance": 6235.07,
      "equity": 6119.17
    },
    {
      "time": "2026-04-30T16:17:21.871078+00:00",
      "balance": 6235.07,
      "equity": 6118.18
    },
    {
      "time": "2026-04-30T16:17:22.895393+00:00",
      "balance": 6235.07,
      "equity": 6114.84
    },
    {
      "time": "2026-04-30T16:17:23.918720+00:00",
      "balance": 6235.07,
      "equity": 6130.29
    },
    {
      "time": "2026-04-30T16:17:24.944437+00:00",
      "balance": 6235.07,
      "equity": 6129.19
    },
    {
      "time": "2026-04-30T16:17:25.971223+00:00",
      "balance": 6235.07,
      "equity": 6148.71
    },
    {
      "time": "2026-04-30T16:17:28.633181+00:00",
      "balance": 6235.07,
      "equity": 6149.38
    },
    {
      "time": "2026-04-30T16:17:29.662458+00:00",
      "balance": 6235.07,
      "equity": 6139.96
    },
    {
      "time": "2026-04-30T16:17:30.686911+00:00",
      "balance": 6235.07,
      "equity": 6139.66
    },
    {
      "time": "2026-04-30T16:17:31.710383+00:00",
      "balance": 6235.07,
      "equity": 6142.09
    },
    {
      "time": "2026-04-30T16:17:32.737941+00:00",
      "balance": 6235.07,
      "equity": 6144.8
    },
    {
      "time": "2026-04-30T16:17:33.765616+00:00",
      "balance": 6235.07,
      "equity": 6156.01
    },
    {
      "time": "2026-04-30T16:17:34.791661+00:00",
      "balance": 6235.07,
      "equity": 6150.82
    },
    {
      "time": "2026-04-30T16:17:35.815309+00:00",
      "balance": 6235.07,
      "equity": 6131.12
    },
    {
      "time": "2026-04-30T16:17:36.840037+00:00",
      "balance": 6235.07,
      "equity": 6119.63
    },
    {
      "time": "2026-04-30T16:17:37.873800+00:00",
      "balance": 6235.07,
      "equity": 6123.35
    },
    {
      "time": "2026-04-30T16:17:38.899133+00:00",
      "balance": 6235.07,
      "equity": 6113.19
    },
    {
      "time": "2026-04-30T16:17:39.922392+00:00",
      "balance": 6235.07,
      "equity": 6121.89
    },
    {
      "time": "2026-04-30T16:17:40.944949+00:00",
      "balance": 6235.07,
      "equity": 6120.62
    },
    {
      "time": "2026-04-30T16:17:41.970239+00:00",
      "balance": 6235.07,
      "equity": 6119.59
    },
    {
      "time": "2026-04-30T16:17:42.995947+00:00",
      "balance": 6235.07,
      "equity": 6127.87
    },
    {
      "time": "2026-04-30T16:17:44.025050+00:00",
      "balance": 6235.07,
      "equity": 6118.91
    },
    {
      "time": "2026-04-30T16:17:45.048914+00:00",
      "balance": 6235.07,
      "equity": 6116.42
    },
    {
      "time": "2026-04-30T16:17:46.073078+00:00",
      "balance": 6235.07,
      "equity": 6110.77
    },
    {
      "time": "2026-04-30T16:17:47.143135+00:00",
      "balance": 6235.07,
      "equity": 6127.08
    },
    {
      "time": "2026-04-30T16:17:48.166460+00:00",
      "balance": 6235.07,
      "equity": 6118.73
    },
    {
      "time": "2026-04-30T16:17:49.193282+00:00",
      "balance": 6235.07,
      "equity": 6118.73
    },
    {
      "time": "2026-04-30T16:17:50.221589+00:00",
      "balance": 6235.07,
      "equity": 6119.96
    },
    {
      "time": "2026-04-30T16:17:51.265303+00:00",
      "balance": 6235.07,
      "equity": 6113.54
    },
    {
      "time": "2026-04-30T16:17:52.289756+00:00",
      "balance": 6235.07,
      "equity": 6128.38
    },
    {
      "time": "2026-04-30T16:17:53.315472+00:00",
      "balance": 6235.07,
      "equity": 6110.69
    },
    {
      "time": "2026-04-30T16:17:54.339739+00:00",
      "balance": 6235.07,
      "equity": 6115.94
    },
    {
      "time": "2026-04-30T16:17:55.368842+00:00",
      "balance": 6235.07,
      "equity": 6119.96
    },
    {
      "time": "2026-04-30T16:17:56.394705+00:00",
      "balance": 6235.07,
      "equity": 6116.81
    },
    {
      "time": "2026-04-30T16:17:57.419195+00:00",
      "balance": 6235.07,
      "equity": 6123.41
    },
    {
      "time": "2026-04-30T16:17:58.443583+00:00",
      "balance": 6235.07,
      "equity": 6117.76
    },
    {
      "time": "2026-04-30T16:17:59.468556+00:00",
      "balance": 6235.07,
      "equity": 6120.81
    },
    {
      "time": "2026-04-30T16:18:00.492675+00:00",
      "balance": 6235.07,
      "equity": 6125.84
    },
    {
      "time": "2026-04-30T16:18:01.519148+00:00",
      "balance": 6235.07,
      "equity": 6122.58
    },
    {
      "time": "2026-04-30T16:18:02.547593+00:00",
      "balance": 6235.07,
      "equity": 6134.19
    },
    {
      "time": "2026-04-30T16:18:03.570711+00:00",
      "balance": 6235.07,
      "equity": 6136.28
    },
    {
      "time": "2026-04-30T16:18:04.594259+00:00",
      "balance": 6235.07,
      "equity": 6135.21
    },
    {
      "time": "2026-04-30T16:18:05.617090+00:00",
      "balance": 6235.07,
      "equity": 6129.59
    },
    {
      "time": "2026-04-30T16:18:06.643241+00:00",
      "balance": 6235.07,
      "equity": 6131.69
    },
    {
      "time": "2026-04-30T16:18:07.673991+00:00",
      "balance": 6235.07,
      "equity": 6110.67
    }
  ],
  "initial_balance": 6019.51,
  "start_time": "2026-04-30T10:05:11.134637+00:00"
}